{"featureCount":4,"formatVersion":1,"histograms":{"meta":[{"arrayParams":{"chunkSize":10000,"length":2,"urlTemplate":"hist-20000-{Chunk}.json"},"basesPerBin":"20000"}],"stats":[{"basesPerBin":"20000","max":4,"mean":2.5}]},"intervals":{"classes":[{"attributes":["Start","End","Strand","Id","Name","Seq_id","Source","Subfeatures","Type"],"isArrayAttr":{"Subfeatures":1}},{"attributes":["Start","End","Strand","Coverage","Id","Identity","Indels","Matches","Mismatches","Name","Seq_id","Source","Subfeatures","Type","Unknowns"],"isArrayAttr":{"Subfeatures":1}},{"attributes":["Start","End","Strand","Id","Name","Score","Seq_id","Source","Target","Type"],"isArrayAttr":{}},{"attributes":["Start","End","Strand","Id","Name","Phase","Score","Seq_id","Source","Target","Type"],"isArrayAttr":{}},{"attributes":["Start","End","Chunk"],"isArrayAttr":{"Sublist":1}}],"count":4,"lazyClass":4,"maxEnd":22876,"minStart":839,"nclist":[[0,839,2933,-1,"tig00014581.g4.t1.path1","tig00014581.g4.t1","tig00014581_overlapping_hits_sub_region","cannabis_loc_scaffold",[[1,839,2933,-1,"100.0","tig00014581.g4.t1.mrna1","100.0","0","1395","0","tig00014581.g4.t1","tig00014581_overlapping_hits_sub_region","cannabis_loc_scaffold",[[2,2493,2933,-1,"tig00014581.g4.t1.mrna1.exon1","tig00014581.g4.t1",100,"tig00014581_overlapping_hits_sub_region","cannabis_loc_scaffold","tig00014581.g4.t1 1 440 +","exon"],[2,2032,2325,-1,"tig00014581.g4.t1.mrna1.exon2","tig00014581.g4.t1",100,"tig00014581_overlapping_hits_sub_region","cannabis_loc_scaffold","tig00014581.g4.t1 441 733 +","exon"],[2,1707,1944,-1,"tig00014581.g4.t1.mrna1.exon3","tig00014581.g4.t1",100,"tig00014581_overlapping_hits_sub_region","cannabis_loc_scaffold","tig00014581.g4.t1 734 970 +","exon"],[2,1470,1617,-1,"tig00014581.g4.t1.mrna1.exon4","tig00014581.g4.t1",100,"tig00014581_overlapping_hits_sub_region","cannabis_loc_scaffold","tig00014581.g4.t1 971 1117 +","exon"],[2,1082,1237,-1,"tig00014581.g4.t1.mrna1.exon5","tig00014581.g4.t1",100,"tig00014581_overlapping_hits_sub_region","cannabis_loc_scaffold","tig00014581.g4.t1 1118 1272 +","exon"],[2,839,962,-1,"tig00014581.g4.t1.mrna1.exon6","tig00014581.g4.t1",100,"tig00014581_overlapping_hits_sub_region","cannabis_loc_scaffold","tig00014581.g4.t1 1273 1395 +","exon"],[3,2493,2933,-1,"tig00014581.g4.t1.mrna1.cds1","tig00014581.g4.t1",0,100,"tig00014581_overlapping_hits_sub_region","cannabis_loc_scaffold","tig00014581.g4.t1 1 440 +","CDS"],[3,2032,2325,-1,"tig00014581.g4.t1.mrna1.cds2","tig00014581.g4.t1",2,100,"tig00014581_overlapping_hits_sub_region","cannabis_loc_scaffold","tig00014581.g4.t1 441 733 +","CDS"],[3,1707,1944,-1,"tig00014581.g4.t1.mrna1.cds3","tig00014581.g4.t1",1,100,"tig00014581_overlapping_hits_sub_region","cannabis_loc_scaffold","tig00014581.g4.t1 734 970 +","CDS"],[3,1470,1617,-1,"tig00014581.g4.t1.mrna1.cds4","tig00014581.g4.t1",1,100,"tig00014581_overlapping_hits_sub_region","cannabis_loc_scaffold","tig00014581.g4.t1 971 1117 +","CDS"],[3,1082,1237,-1,"tig00014581.g4.t1.mrna1.cds5","tig00014581.g4.t1",1,100,"tig00014581_overlapping_hits_sub_region","cannabis_loc_scaffold","tig00014581.g4.t1 1118 1272 +","CDS"],[3,839,962,-1,"tig00014581.g4.t1.mrna1.cds6","tig00014581.g4.t1",0,100,"tig00014581_overlapping_hits_sub_region","cannabis_loc_scaffold","tig00014581.g4.t1 1273 1395 +","CDS"]],"mRNA","0"]],"gene"],[0,4615,6985,1,"tig00014581.g5.t1.path1","tig00014581.g5.t1","tig00014581_overlapping_hits_sub_region","cannabis_loc_scaffold",[[1,4615,6985,1,"100.0","tig00014581.g5.t1.mrna1","100.0","0","534","0","tig00014581.g5.t1","tig00014581_overlapping_hits_sub_region","cannabis_loc_scaffold",[[2,4615,4664,1,"tig00014581.g5.t1.mrna1.exon1","tig00014581.g5.t1",100,"tig00014581_overlapping_hits_sub_region","cannabis_loc_scaffold","tig00014581.g5.t1 1 49 +","exon"],[2,5191,5450,1,"tig00014581.g5.t1.mrna1.exon2","tig00014581.g5.t1",100,"tig00014581_overlapping_hits_sub_region","cannabis_loc_scaffold","tig00014581.g5.t1 50 308 +","exon"],[2,5766,5849,1,"tig00014581.g5.t1.mrna1.exon3","tig00014581.g5.t1",100,"tig00014581_overlapping_hits_sub_region","cannabis_loc_scaffold","tig00014581.g5.t1 309 391 +","exon"],[2,6698,6767,1,"tig00014581.g5.t1.mrna1.exon4","tig00014581.g5.t1",100,"tig00014581_overlapping_hits_sub_region","cannabis_loc_scaffold","tig00014581.g5.t1 392 460 +","exon"],[2,6911,6985,1,"tig00014581.g5.t1.mrna1.exon5","tig00014581.g5.t1",100,"tig00014581_overlapping_hits_sub_region","cannabis_loc_scaffold","tig00014581.g5.t1 461 534 +","exon"],[3,4615,4664,1,"tig00014581.g5.t1.mrna1.cds1","tig00014581.g5.t1",0,100,"tig00014581_overlapping_hits_sub_region","cannabis_loc_scaffold","tig00014581.g5.t1 1 49 +","CDS"],[3,5191,5450,1,"tig00014581.g5.t1.mrna1.cds2","tig00014581.g5.t1",1,100,"tig00014581_overlapping_hits_sub_region","cannabis_loc_scaffold","tig00014581.g5.t1 50 308 +","CDS"],[3,5766,5849,1,"tig00014581.g5.t1.mrna1.cds3","tig00014581.g5.t1",2,100,"tig00014581_overlapping_hits_sub_region","cannabis_loc_scaffold","tig00014581.g5.t1 309 391 +","CDS"],[3,6698,6767,1,"tig00014581.g5.t1.mrna1.cds4","tig00014581.g5.t1",1,100,"tig00014581_overlapping_hits_sub_region","cannabis_loc_scaffold","tig00014581.g5.t1 392 460 +","CDS"],[3,6911,6985,1,"tig00014581.g5.t1.mrna1.cds5","tig00014581.g5.t1",1,100,"tig00014581_overlapping_hits_sub_region","cannabis_loc_scaffold","tig00014581.g5.t1 461 534 +","CDS"]],"mRNA","0"]],"gene"],[0,10281,14634,1,"tig00014581.g6.t1.path1","tig00014581.g6.t1","tig00014581_overlapping_hits_sub_region","cannabis_loc_scaffold",[[1,10281,14634,1,"100.0","tig00014581.g6.t1.mrna1","100.0","0","3294","0","tig00014581.g6.t1","tig00014581_overlapping_hits_sub_region","cannabis_loc_scaffold",[[2,10281,10448,1,"tig00014581.g6.t1.mrna1.exon1","tig00014581.g6.t1",100,"tig00014581_overlapping_hits_sub_region","cannabis_loc_scaffold","tig00014581.g6.t1 1 167 +","exon"],[2,10556,11903,1,"tig00014581.g6.t1.mrna1.exon2","tig00014581.g6.t1",100,"tig00014581_overlapping_hits_sub_region","cannabis_loc_scaffold","tig00014581.g6.t1 168 1514 +","exon"],[2,12148,12449,1,"tig00014581.g6.t1.mrna1.exon3","tig00014581.g6.t1",100,"tig00014581_overlapping_hits_sub_region","cannabis_loc_scaffold","tig00014581.g6.t1 1515 1815 +","exon"],[2,12548,12620,1,"tig00014581.g6.t1.mrna1.exon4","tig00014581.g6.t1",100,"tig00014581_overlapping_hits_sub_region","cannabis_loc_scaffold","tig00014581.g6.t1 1816 1887 +","exon"],[2,12758,12959,1,"tig00014581.g6.t1.mrna1.exon5","tig00014581.g6.t1",100,"tig00014581_overlapping_hits_sub_region","cannabis_loc_scaffold","tig00014581.g6.t1 1888 2088 +","exon"],[2,13053,13805,1,"tig00014581.g6.t1.mrna1.exon6","tig00014581.g6.t1",100,"tig00014581_overlapping_hits_sub_region","cannabis_loc_scaffold","tig00014581.g6.t1 2089 2840 +","exon"],[2,14072,14184,1,"tig00014581.g6.t1.mrna1.exon7","tig00014581.g6.t1",100,"tig00014581_overlapping_hits_sub_region","cannabis_loc_scaffold","tig00014581.g6.t1 2841 2952 +","exon"],[2,14292,14634,1,"tig00014581.g6.t1.mrna1.exon8","tig00014581.g6.t1",100,"tig00014581_overlapping_hits_sub_region","cannabis_loc_scaffold","tig00014581.g6.t1 2953 3294 +","exon"],[3,10281,10448,1,"tig00014581.g6.t1.mrna1.cds1","tig00014581.g6.t1",0,100,"tig00014581_overlapping_hits_sub_region","cannabis_loc_scaffold","tig00014581.g6.t1 1 167 +","CDS"],[3,10556,11903,1,"tig00014581.g6.t1.mrna1.cds2","tig00014581.g6.t1",2,100,"tig00014581_overlapping_hits_sub_region","cannabis_loc_scaffold","tig00014581.g6.t1 168 1514 +","CDS"],[3,12148,12449,1,"tig00014581.g6.t1.mrna1.cds3","tig00014581.g6.t1",2,100,"tig00014581_overlapping_hits_sub_region","cannabis_loc_scaffold","tig00014581.g6.t1 1515 1815 +","CDS"],[3,12548,12620,1,"tig00014581.g6.t1.mrna1.cds4","tig00014581.g6.t1",0,100,"tig00014581_overlapping_hits_sub_region","cannabis_loc_scaffold","tig00014581.g6.t1 1816 1887 +","CDS"],[3,12758,12959,1,"tig00014581.g6.t1.mrna1.cds5","tig00014581.g6.t1",0,100,"tig00014581_overlapping_hits_sub_region","cannabis_loc_scaffold","tig00014581.g6.t1 1888 2088 +","CDS"],[3,13053,13805,1,"tig00014581.g6.t1.mrna1.cds6","tig00014581.g6.t1",0,100,"tig00014581_overlapping_hits_sub_region","cannabis_loc_scaffold","tig00014581.g6.t1 2089 2840 +","CDS"],[3,14072,14184,1,"tig00014581.g6.t1.mrna1.cds7","tig00014581.g6.t1",2,100,"tig00014581_overlapping_hits_sub_region","cannabis_loc_scaffold","tig00014581.g6.t1 2841 2952 +","CDS"],[3,14292,14634,1,"tig00014581.g6.t1.mrna1.cds8","tig00014581.g6.t1",0,100,"tig00014581_overlapping_hits_sub_region","cannabis_loc_scaffold","tig00014581.g6.t1 2953 3294 +","CDS"]],"mRNA","0"]],"gene"],[0,15989,22876,-1,"tig00014581.g7.t1.path1","tig00014581.g7.t1","tig00014581_overlapping_hits_sub_region","cannabis_loc_scaffold",[[1,15989,22876,-1,"100.0","tig00014581.g7.t1.mrna1","100.0","0","3213","0","tig00014581.g7.t1","tig00014581_overlapping_hits_sub_region","cannabis_loc_scaffold",[[2,22602,22876,-1,"tig00014581.g7.t1.mrna1.exon1","tig00014581.g7.t1",100,"tig00014581_overlapping_hits_sub_region","cannabis_loc_scaffold","tig00014581.g7.t1 1 274 +","exon"],[2,22207,22262,-1,"tig00014581.g7.t1.mrna1.exon2","tig00014581.g7.t1",100,"tig00014581_overlapping_hits_sub_region","cannabis_loc_scaffold","tig00014581.g7.t1 275 329 +","exon"],[2,21659,21729,-1,"tig00014581.g7.t1.mrna1.exon3","tig00014581.g7.t1",100,"tig00014581_overlapping_hits_sub_region","cannabis_loc_scaffold","tig00014581.g7.t1 330 399 +","exon"],[2,21132,21206,-1,"tig00014581.g7.t1.mrna1.exon4","tig00014581.g7.t1",100,"tig00014581_overlapping_hits_sub_region","cannabis_loc_scaffold","tig00014581.g7.t1 400 473 +","exon"],[2,20793,21041,-1,"tig00014581.g7.t1.mrna1.exon5","tig00014581.g7.t1",100,"tig00014581_overlapping_hits_sub_region","cannabis_loc_scaffold","tig00014581.g7.t1 474 721 +","exon"],[2,20622,20708,-1,"tig00014581.g7.t1.mrna1.exon6","tig00014581.g7.t1",100,"tig00014581_overlapping_hits_sub_region","cannabis_loc_scaffold","tig00014581.g7.t1 722 807 +","exon"],[2,20106,20507,-1,"tig00014581.g7.t1.mrna1.exon7","tig00014581.g7.t1",100,"tig00014581_overlapping_hits_sub_region","cannabis_loc_scaffold","tig00014581.g7.t1 808 1208 +","exon"],[2,19887,19964,-1,"tig00014581.g7.t1.mrna1.exon8","tig00014581.g7.t1",100,"tig00014581_overlapping_hits_sub_region","cannabis_loc_scaffold","tig00014581.g7.t1 1209 1285 +","exon"],[2,19629,19710,-1,"tig00014581.g7.t1.mrna1.exon9","tig00014581.g7.t1",100,"tig00014581_overlapping_hits_sub_region","cannabis_loc_scaffold","tig00014581.g7.t1 1286 1366 +","exon"],[2,18908,19321,-1,"tig00014581.g7.t1.mrna1.exon10","tig00014581.g7.t1",100,"tig00014581_overlapping_hits_sub_region","cannabis_loc_scaffold","tig00014581.g7.t1 1367 1779 +","exon"],[2,18521,18656,-1,"tig00014581.g7.t1.mrna1.exon11","tig00014581.g7.t1",100,"tig00014581_overlapping_hits_sub_region","cannabis_loc_scaffold","tig00014581.g7.t1 1780 1914 +","exon"],[2,18174,18329,-1,"tig00014581.g7.t1.mrna1.exon12","tig00014581.g7.t1",100,"tig00014581_overlapping_hits_sub_region","cannabis_loc_scaffold","tig00014581.g7.t1 1915 2069 +","exon"],[2,17982,18103,-1,"tig00014581.g7.t1.mrna1.exon13","tig00014581.g7.t1",100,"tig00014581_overlapping_hits_sub_region","cannabis_loc_scaffold","tig00014581.g7.t1 2070 2190 +","exon"],[2,17620,17720,-1,"tig00014581.g7.t1.mrna1.exon14","tig00014581.g7.t1",100,"tig00014581_overlapping_hits_sub_region","cannabis_loc_scaffold","tig00014581.g7.t1 2191 2290 +","exon"],[2,17446,17512,-1,"tig00014581.g7.t1.mrna1.exon15","tig00014581.g7.t1",100,"tig00014581_overlapping_hits_sub_region","cannabis_loc_scaffold","tig00014581.g7.t1 2291 2356 +","exon"],[2,17115,17259,-1,"tig00014581.g7.t1.mrna1.exon16","tig00014581.g7.t1",100,"tig00014581_overlapping_hits_sub_region","cannabis_loc_scaffold","tig00014581.g7.t1 2357 2500 +","exon"],[2,16691,17014,-1,"tig00014581.g7.t1.mrna1.exon17","tig00014581.g7.t1",100,"tig00014581_overlapping_hits_sub_region","cannabis_loc_scaffold","tig00014581.g7.t1 2501 2823 +","exon"],[2,16464,16564,-1,"tig00014581.g7.t1.mrna1.exon18","tig00014581.g7.t1",100,"tig00014581_overlapping_hits_sub_region","cannabis_loc_scaffold","tig00014581.g7.t1 2824 2923 +","exon"],[2,16192,16343,-1,"tig00014581.g7.t1.mrna1.exon19","tig00014581.g7.t1",100,"tig00014581_overlapping_hits_sub_region","cannabis_loc_scaffold","tig00014581.g7.t1 2924 3074 +","exon"],[2,15989,16128,-1,"tig00014581.g7.t1.mrna1.exon20","tig00014581.g7.t1",100,"tig00014581_overlapping_hits_sub_region","cannabis_loc_scaffold","tig00014581.g7.t1 3075 3213 +","exon"],[3,22602,22876,-1,"tig00014581.g7.t1.mrna1.cds1","tig00014581.g7.t1",0,100,"tig00014581_overlapping_hits_sub_region","cannabis_loc_scaffold","tig00014581.g7.t1 1 274 +","CDS"],[3,22207,22262,-1,"tig00014581.g7.t1.mrna1.cds2","tig00014581.g7.t1",1,100,"tig00014581_overlapping_hits_sub_region","cannabis_loc_scaffold","tig00014581.g7.t1 275 329 +","CDS"],[3,21659,21729,-1,"tig00014581.g7.t1.mrna1.cds3","tig00014581.g7.t1",2,100,"tig00014581_overlapping_hits_sub_region","cannabis_loc_scaffold","tig00014581.g7.t1 330 399 +","CDS"],[3,21132,21206,-1,"tig00014581.g7.t1.mrna1.cds4","tig00014581.g7.t1",0,100,"tig00014581_overlapping_hits_sub_region","cannabis_loc_scaffold","tig00014581.g7.t1 400 473 +","CDS"],[3,20793,21041,-1,"tig00014581.g7.t1.mrna1.cds5","tig00014581.g7.t1",2,100,"tig00014581_overlapping_hits_sub_region","cannabis_loc_scaffold","tig00014581.g7.t1 474 721 +","CDS"],[3,20622,20708,-1,"tig00014581.g7.t1.mrna1.cds6","tig00014581.g7.t1",1,100,"tig00014581_overlapping_hits_sub_region","cannabis_loc_scaffold","tig00014581.g7.t1 722 807 +","CDS"],[3,20106,20507,-1,"tig00014581.g7.t1.mrna1.cds7","tig00014581.g7.t1",0,100,"tig00014581_overlapping_hits_sub_region","cannabis_loc_scaffold","tig00014581.g7.t1 808 1208 +","CDS"],[3,19887,19964,-1,"tig00014581.g7.t1.mrna1.cds8","tig00014581.g7.t1",2,100,"tig00014581_overlapping_hits_sub_region","cannabis_loc_scaffold","tig00014581.g7.t1 1209 1285 +","CDS"],[3,19629,19710,-1,"tig00014581.g7.t1.mrna1.cds9","tig00014581.g7.t1",1,100,"tig00014581_overlapping_hits_sub_region","cannabis_loc_scaffold","tig00014581.g7.t1 1286 1366 +","CDS"],[3,18908,19321,-1,"tig00014581.g7.t1.mrna1.cds10","tig00014581.g7.t1",1,100,"tig00014581_overlapping_hits_sub_region","cannabis_loc_scaffold","tig00014581.g7.t1 1367 1779 +","CDS"],[3,18521,18656,-1,"tig00014581.g7.t1.mrna1.cds11","tig00014581.g7.t1",0,100,"tig00014581_overlapping_hits_sub_region","cannabis_loc_scaffold","tig00014581.g7.t1 1780 1914 +","CDS"],[3,18174,18329,-1,"tig00014581.g7.t1.mrna1.cds12","tig00014581.g7.t1",0,100,"tig00014581_overlapping_hits_sub_region","cannabis_loc_scaffold","tig00014581.g7.t1 1915 2069 +","CDS"],[3,17982,18103,-1,"tig00014581.g7.t1.mrna1.cds13","tig00014581.g7.t1",2,100,"tig00014581_overlapping_hits_sub_region","cannabis_loc_scaffold","tig00014581.g7.t1 2070 2190 +","CDS"],[3,17620,17720,-1,"tig00014581.g7.t1.mrna1.cds14","tig00014581.g7.t1",0,100,"tig00014581_overlapping_hits_sub_region","cannabis_loc_scaffold","tig00014581.g7.t1 2191 2290 +","CDS"],[3,17446,17512,-1,"tig00014581.g7.t1.mrna1.cds15","tig00014581.g7.t1",1,100,"tig00014581_overlapping_hits_sub_region","cannabis_loc_scaffold","tig00014581.g7.t1 2291 2356 +","CDS"],[3,17115,17259,-1,"tig00014581.g7.t1.mrna1.cds16","tig00014581.g7.t1",1,100,"tig00014581_overlapping_hits_sub_region","cannabis_loc_scaffold","tig00014581.g7.t1 2357 2500 +","CDS"],[3,16691,17014,-1,"tig00014581.g7.t1.mrna1.cds17","tig00014581.g7.t1",1,100,"tig00014581_overlapping_hits_sub_region","cannabis_loc_scaffold","tig00014581.g7.t1 2501 2823 +","CDS"],[3,16464,16564,-1,"tig00014581.g7.t1.mrna1.cds18","tig00014581.g7.t1",0,100,"tig00014581_overlapping_hits_sub_region","cannabis_loc_scaffold","tig00014581.g7.t1 2824 2923 +","CDS"],[3,16192,16343,-1,"tig00014581.g7.t1.mrna1.cds19","tig00014581.g7.t1",1,100,"tig00014581_overlapping_hits_sub_region","cannabis_loc_scaffold","tig00014581.g7.t1 2924 3074 +","CDS"],[3,15989,16128,-1,"tig00014581.g7.t1.mrna1.cds20","tig00014581.g7.t1",2,100,"tig00014581_overlapping_hits_sub_region","cannabis_loc_scaffold","tig00014581.g7.t1 3075 3213 +","CDS"]],"mRNA","0"]],"gene"]],"urlTemplate":"lf-{Chunk}.json"}}