{"featureCount":4,"formatVersion":1,"histograms":{"meta":[{"arrayParams":{"chunkSize":10000,"length":2,"urlTemplate":"hist-10000-{Chunk}.json"},"basesPerBin":"10000"}],"stats":[{"basesPerBin":"10000","max":2,"mean":2}]},"intervals":{"classes":[{"attributes":["Start","End","Strand","Id","Name","Seq_id","Source","Subfeatures","Type"],"isArrayAttr":{"Subfeatures":1}},{"attributes":["Start","End","Strand","Coverage","Id","Identity","Indels","Matches","Mismatches","Name","Seq_id","Source","Subfeatures","Type","Unknowns"],"isArrayAttr":{"Subfeatures":1}},{"attributes":["Start","End","Strand","Id","Name","Score","Seq_id","Source","Target","Type"],"isArrayAttr":{}},{"attributes":["Start","End","Strand","Id","Name","Phase","Score","Seq_id","Source","Target","Type"],"isArrayAttr":{}},{"attributes":["Start","End","Chunk"],"isArrayAttr":{"Sublist":1}}],"count":4,"lazyClass":4,"maxEnd":13349,"minStart":50,"nclist":[[0,50,3247,1,"tig00045808.g1.t1.path1","tig00045808.g1.t1","tig00045808_overlapping_hits_sub_region","cannabis_loc_scaffold",[[1,50,3247,1,"100.0","tig00045808.g1.t1.mrna1","100.0","0","1200","0","tig00045808.g1.t1","tig00045808_overlapping_hits_sub_region","cannabis_loc_scaffold",[[2,50,194,1,"tig00045808.g1.t1.mrna1.exon1","tig00045808.g1.t1",100,"tig00045808_overlapping_hits_sub_region","cannabis_loc_scaffold","tig00045808.g1.t1 1 144 +","exon"],[2,295,470,1,"tig00045808.g1.t1.mrna1.exon2","tig00045808.g1.t1",100,"tig00045808_overlapping_hits_sub_region","cannabis_loc_scaffold","tig00045808.g1.t1 145 319 +","exon"],[2,584,690,1,"tig00045808.g1.t1.mrna1.exon3","tig00045808.g1.t1",100,"tig00045808_overlapping_hits_sub_region","cannabis_loc_scaffold","tig00045808.g1.t1 320 425 +","exon"],[2,842,1077,1,"tig00045808.g1.t1.mrna1.exon4","tig00045808.g1.t1",100,"tig00045808_overlapping_hits_sub_region","cannabis_loc_scaffold","tig00045808.g1.t1 426 660 +","exon"],[2,1157,1219,1,"tig00045808.g1.t1.mrna1.exon5","tig00045808.g1.t1",100,"tig00045808_overlapping_hits_sub_region","cannabis_loc_scaffold","tig00045808.g1.t1 661 722 +","exon"],[2,2279,2296,1,"tig00045808.g1.t1.mrna1.exon6","tig00045808.g1.t1",100,"tig00045808_overlapping_hits_sub_region","cannabis_loc_scaffold","tig00045808.g1.t1 723 739 +","exon"],[2,2369,2507,1,"tig00045808.g1.t1.mrna1.exon7","tig00045808.g1.t1",100,"tig00045808_overlapping_hits_sub_region","cannabis_loc_scaffold","tig00045808.g1.t1 740 877 +","exon"],[2,2612,2679,1,"tig00045808.g1.t1.mrna1.exon8","tig00045808.g1.t1",100,"tig00045808_overlapping_hits_sub_region","cannabis_loc_scaffold","tig00045808.g1.t1 878 944 +","exon"],[2,2850,3020,1,"tig00045808.g1.t1.mrna1.exon9","tig00045808.g1.t1",100,"tig00045808_overlapping_hits_sub_region","cannabis_loc_scaffold","tig00045808.g1.t1 945 1114 +","exon"],[2,3087,3156,1,"tig00045808.g1.t1.mrna1.exon10","tig00045808.g1.t1",100,"tig00045808_overlapping_hits_sub_region","cannabis_loc_scaffold","tig00045808.g1.t1 1115 1183 +","exon"],[2,3230,3247,1,"tig00045808.g1.t1.mrna1.exon11","tig00045808.g1.t1",100,"tig00045808_overlapping_hits_sub_region","cannabis_loc_scaffold","tig00045808.g1.t1 1184 1200 +","exon"],[3,50,194,1,"tig00045808.g1.t1.mrna1.cds1","tig00045808.g1.t1",0,100,"tig00045808_overlapping_hits_sub_region","cannabis_loc_scaffold","tig00045808.g1.t1 1 144 +","CDS"],[3,295,470,1,"tig00045808.g1.t1.mrna1.cds2","tig00045808.g1.t1",0,100,"tig00045808_overlapping_hits_sub_region","cannabis_loc_scaffold","tig00045808.g1.t1 145 319 +","CDS"],[3,584,690,1,"tig00045808.g1.t1.mrna1.cds3","tig00045808.g1.t1",1,100,"tig00045808_overlapping_hits_sub_region","cannabis_loc_scaffold","tig00045808.g1.t1 320 425 +","CDS"],[3,842,1077,1,"tig00045808.g1.t1.mrna1.cds4","tig00045808.g1.t1",2,100,"tig00045808_overlapping_hits_sub_region","cannabis_loc_scaffold","tig00045808.g1.t1 426 660 +","CDS"],[3,1157,1219,1,"tig00045808.g1.t1.mrna1.cds5","tig00045808.g1.t1",0,100,"tig00045808_overlapping_hits_sub_region","cannabis_loc_scaffold","tig00045808.g1.t1 661 722 +","CDS"],[3,2279,2296,1,"tig00045808.g1.t1.mrna1.cds6","tig00045808.g1.t1",2,100,"tig00045808_overlapping_hits_sub_region","cannabis_loc_scaffold","tig00045808.g1.t1 723 739 +","CDS"],[3,2369,2507,1,"tig00045808.g1.t1.mrna1.cds7","tig00045808.g1.t1",1,100,"tig00045808_overlapping_hits_sub_region","cannabis_loc_scaffold","tig00045808.g1.t1 740 877 +","CDS"],[3,2612,2679,1,"tig00045808.g1.t1.mrna1.cds8","tig00045808.g1.t1",1,100,"tig00045808_overlapping_hits_sub_region","cannabis_loc_scaffold","tig00045808.g1.t1 878 944 +","CDS"],[3,2850,3020,1,"tig00045808.g1.t1.mrna1.cds9","tig00045808.g1.t1",2,100,"tig00045808_overlapping_hits_sub_region","cannabis_loc_scaffold","tig00045808.g1.t1 945 1114 +","CDS"],[3,3087,3156,1,"tig00045808.g1.t1.mrna1.cds10","tig00045808.g1.t1",1,100,"tig00045808_overlapping_hits_sub_region","cannabis_loc_scaffold","tig00045808.g1.t1 1115 1183 +","CDS"],[3,3230,3247,1,"tig00045808.g1.t1.mrna1.cds11","tig00045808.g1.t1",1,100,"tig00045808_overlapping_hits_sub_region","cannabis_loc_scaffold","tig00045808.g1.t1 1184 1200 +","CDS"]],"mRNA","0"]],"gene"],[0,3607,6116,-1,"tig00045808.g2.t1.path1","tig00045808.g2.t1","tig00045808_overlapping_hits_sub_region","cannabis_loc_scaffold",[[1,3607,6116,-1,"100.0","tig00045808.g2.t1.mrna1","100.0","0","1179","0","tig00045808.g2.t1","tig00045808_overlapping_hits_sub_region","cannabis_loc_scaffold",[[2,5968,6116,-1,"tig00045808.g2.t1.mrna1.exon1","tig00045808.g2.t1",100,"tig00045808_overlapping_hits_sub_region","cannabis_loc_scaffold","tig00045808.g2.t1 1 148 +","exon"],[2,5800,5862,-1,"tig00045808.g2.t1.mrna1.exon2","tig00045808.g2.t1",100,"tig00045808_overlapping_hits_sub_region","cannabis_loc_scaffold","tig00045808.g2.t1 149 210 +","exon"],[2,5545,5632,-1,"tig00045808.g2.t1.mrna1.exon3","tig00045808.g2.t1",100,"tig00045808_overlapping_hits_sub_region","cannabis_loc_scaffold","tig00045808.g2.t1 211 297 +","exon"],[2,5321,5365,-1,"tig00045808.g2.t1.mrna1.exon4","tig00045808.g2.t1",100,"tig00045808_overlapping_hits_sub_region","cannabis_loc_scaffold","tig00045808.g2.t1 298 341 +","exon"],[2,4597,4735,-1,"tig00045808.g2.t1.mrna1.exon5","tig00045808.g2.t1",100,"tig00045808_overlapping_hits_sub_region","cannabis_loc_scaffold","tig00045808.g2.t1 342 479 +","exon"],[2,4414,4538,-1,"tig00045808.g2.t1.mrna1.exon6","tig00045808.g2.t1",100,"tig00045808_overlapping_hits_sub_region","cannabis_loc_scaffold","tig00045808.g2.t1 480 603 +","exon"],[2,4084,4340,-1,"tig00045808.g2.t1.mrna1.exon7","tig00045808.g2.t1",100,"tig00045808_overlapping_hits_sub_region","cannabis_loc_scaffold","tig00045808.g2.t1 604 859 +","exon"],[2,3607,3927,-1,"tig00045808.g2.t1.mrna1.exon8","tig00045808.g2.t1",100,"tig00045808_overlapping_hits_sub_region","cannabis_loc_scaffold","tig00045808.g2.t1 860 1179 +","exon"],[3,5968,6116,-1,"tig00045808.g2.t1.mrna1.cds1","tig00045808.g2.t1",0,100,"tig00045808_overlapping_hits_sub_region","cannabis_loc_scaffold","tig00045808.g2.t1 1 148 +","CDS"],[3,5800,5862,-1,"tig00045808.g2.t1.mrna1.cds2","tig00045808.g2.t1",1,100,"tig00045808_overlapping_hits_sub_region","cannabis_loc_scaffold","tig00045808.g2.t1 149 210 +","CDS"],[3,5545,5632,-1,"tig00045808.g2.t1.mrna1.cds3","tig00045808.g2.t1",0,100,"tig00045808_overlapping_hits_sub_region","cannabis_loc_scaffold","tig00045808.g2.t1 211 297 +","CDS"],[3,5321,5365,-1,"tig00045808.g2.t1.mrna1.cds4","tig00045808.g2.t1",0,100,"tig00045808_overlapping_hits_sub_region","cannabis_loc_scaffold","tig00045808.g2.t1 298 341 +","CDS"],[3,4597,4735,-1,"tig00045808.g2.t1.mrna1.cds5","tig00045808.g2.t1",2,100,"tig00045808_overlapping_hits_sub_region","cannabis_loc_scaffold","tig00045808.g2.t1 342 479 +","CDS"],[3,4414,4538,-1,"tig00045808.g2.t1.mrna1.cds6","tig00045808.g2.t1",2,100,"tig00045808_overlapping_hits_sub_region","cannabis_loc_scaffold","tig00045808.g2.t1 480 603 +","CDS"],[3,4084,4340,-1,"tig00045808.g2.t1.mrna1.cds7","tig00045808.g2.t1",0,100,"tig00045808_overlapping_hits_sub_region","cannabis_loc_scaffold","tig00045808.g2.t1 604 859 +","CDS"],[3,3607,3927,-1,"tig00045808.g2.t1.mrna1.cds8","tig00045808.g2.t1",1,100,"tig00045808_overlapping_hits_sub_region","cannabis_loc_scaffold","tig00045808.g2.t1 860 1179 +","CDS"]],"mRNA","0"]],"gene"],[0,10024,11840,1,"tig00045808.g3.t1.path1","tig00045808.g3.t1","tig00045808_overlapping_hits_sub_region","cannabis_loc_scaffold",[[1,10024,11840,1,"100.0","tig00045808.g3.t1.mrna1","100.0","0","810","0","tig00045808.g3.t1","tig00045808_overlapping_hits_sub_region","cannabis_loc_scaffold",[[2,10024,10070,1,"tig00045808.g3.t1.mrna1.exon1","tig00045808.g3.t1",100,"tig00045808_overlapping_hits_sub_region","cannabis_loc_scaffold","tig00045808.g3.t1 1 46 +","exon"],[2,10222,10297,1,"tig00045808.g3.t1.mrna1.exon2","tig00045808.g3.t1",100,"tig00045808_overlapping_hits_sub_region","cannabis_loc_scaffold","tig00045808.g3.t1 47 121 +","exon"],[2,10379,10479,1,"tig00045808.g3.t1.mrna1.exon3","tig00045808.g3.t1",100,"tig00045808_overlapping_hits_sub_region","cannabis_loc_scaffold","tig00045808.g3.t1 122 221 +","exon"],[2,10674,10717,1,"tig00045808.g3.t1.mrna1.exon4","tig00045808.g3.t1",100,"tig00045808_overlapping_hits_sub_region","cannabis_loc_scaffold","tig00045808.g3.t1 222 264 +","exon"],[2,10810,10963,1,"tig00045808.g3.t1.mrna1.exon5","tig00045808.g3.t1",100,"tig00045808_overlapping_hits_sub_region","cannabis_loc_scaffold","tig00045808.g3.t1 265 417 +","exon"],[2,11026,11069,1,"tig00045808.g3.t1.mrna1.exon6","tig00045808.g3.t1",100,"tig00045808_overlapping_hits_sub_region","cannabis_loc_scaffold","tig00045808.g3.t1 418 460 +","exon"],[2,11162,11237,1,"tig00045808.g3.t1.mrna1.exon7","tig00045808.g3.t1",100,"tig00045808_overlapping_hits_sub_region","cannabis_loc_scaffold","tig00045808.g3.t1 461 535 +","exon"],[2,11317,11417,1,"tig00045808.g3.t1.mrna1.exon8","tig00045808.g3.t1",100,"tig00045808_overlapping_hits_sub_region","cannabis_loc_scaffold","tig00045808.g3.t1 536 635 +","exon"],[2,11665,11840,1,"tig00045808.g3.t1.mrna1.exon9","tig00045808.g3.t1",100,"tig00045808_overlapping_hits_sub_region","cannabis_loc_scaffold","tig00045808.g3.t1 636 810 +","exon"],[3,10024,10070,1,"tig00045808.g3.t1.mrna1.cds1","tig00045808.g3.t1",0,100,"tig00045808_overlapping_hits_sub_region","cannabis_loc_scaffold","tig00045808.g3.t1 1 46 +","CDS"],[3,10222,10297,1,"tig00045808.g3.t1.mrna1.cds2","tig00045808.g3.t1",1,100,"tig00045808_overlapping_hits_sub_region","cannabis_loc_scaffold","tig00045808.g3.t1 47 121 +","CDS"],[3,10379,10479,1,"tig00045808.g3.t1.mrna1.cds3","tig00045808.g3.t1",1,100,"tig00045808_overlapping_hits_sub_region","cannabis_loc_scaffold","tig00045808.g3.t1 122 221 +","CDS"],[3,10674,10717,1,"tig00045808.g3.t1.mrna1.cds4","tig00045808.g3.t1",2,100,"tig00045808_overlapping_hits_sub_region","cannabis_loc_scaffold","tig00045808.g3.t1 222 264 +","CDS"],[3,10810,10963,1,"tig00045808.g3.t1.mrna1.cds5","tig00045808.g3.t1",0,100,"tig00045808_overlapping_hits_sub_region","cannabis_loc_scaffold","tig00045808.g3.t1 265 417 +","CDS"],[3,11026,11069,1,"tig00045808.g3.t1.mrna1.cds6","tig00045808.g3.t1",0,100,"tig00045808_overlapping_hits_sub_region","cannabis_loc_scaffold","tig00045808.g3.t1 418 460 +","CDS"],[3,11162,11237,1,"tig00045808.g3.t1.mrna1.cds7","tig00045808.g3.t1",1,100,"tig00045808_overlapping_hits_sub_region","cannabis_loc_scaffold","tig00045808.g3.t1 461 535 +","CDS"],[3,11317,11417,1,"tig00045808.g3.t1.mrna1.cds8","tig00045808.g3.t1",1,100,"tig00045808_overlapping_hits_sub_region","cannabis_loc_scaffold","tig00045808.g3.t1 536 635 +","CDS"],[3,11665,11840,1,"tig00045808.g3.t1.mrna1.cds9","tig00045808.g3.t1",2,100,"tig00045808_overlapping_hits_sub_region","cannabis_loc_scaffold","tig00045808.g3.t1 636 810 +","CDS"]],"mRNA","0"]],"gene"],[0,12397,13349,-1,"tig00045808.g4.t1.path1","tig00045808.g4.t1","tig00045808_overlapping_hits_sub_region","cannabis_loc_scaffold",[[1,12397,13349,-1,"100.0","tig00045808.g4.t1.mrna1","100.0","0","732","0","tig00045808.g4.t1","tig00045808_overlapping_hits_sub_region","cannabis_loc_scaffold",[[2,13231,13349,-1,"tig00045808.g4.t1.mrna1.exon1","tig00045808.g4.t1",100,"tig00045808_overlapping_hits_sub_region","cannabis_loc_scaffold","tig00045808.g4.t1 1 118 +","exon"],[2,13086,13163,-1,"tig00045808.g4.t1.mrna1.exon2","tig00045808.g4.t1",100,"tig00045808_overlapping_hits_sub_region","cannabis_loc_scaffold","tig00045808.g4.t1 119 195 +","exon"],[2,12397,12934,-1,"tig00045808.g4.t1.mrna1.exon3","tig00045808.g4.t1",100,"tig00045808_overlapping_hits_sub_region","cannabis_loc_scaffold","tig00045808.g4.t1 196 732 +","exon"],[3,13231,13349,-1,"tig00045808.g4.t1.mrna1.cds1","tig00045808.g4.t1",0,100,"tig00045808_overlapping_hits_sub_region","cannabis_loc_scaffold","tig00045808.g4.t1 1 118 +","CDS"],[3,13086,13163,-1,"tig00045808.g4.t1.mrna1.cds2","tig00045808.g4.t1",1,100,"tig00045808_overlapping_hits_sub_region","cannabis_loc_scaffold","tig00045808.g4.t1 119 195 +","CDS"],[3,12397,12934,-1,"tig00045808.g4.t1.mrna1.cds3","tig00045808.g4.t1",0,100,"tig00045808_overlapping_hits_sub_region","cannabis_loc_scaffold","tig00045808.g4.t1 196 732 +","CDS"]],"mRNA","0"]],"gene"]],"urlTemplate":"lf-{Chunk}.json"}}