{"featureCount":2,"formatVersion":1,"histograms":{"meta":[{"arrayParams":{"chunkSize":10000,"length":1,"urlTemplate":"hist-50000-{Chunk}.json"},"basesPerBin":"50000"}],"stats":[{"basesPerBin":"50000","max":2,"mean":2}]},"intervals":{"classes":[{"attributes":["Start","End","Strand","Id","Name","Seq_id","Source","Subfeatures","Type"],"isArrayAttr":{"Subfeatures":1}},{"attributes":["Start","End","Strand","Coverage","Id","Identity","Indels","Matches","Mismatches","Name","Seq_id","Source","Subfeatures","Type","Unknowns"],"isArrayAttr":{"Subfeatures":1}},{"attributes":["Start","End","Strand","Id","Name","Score","Seq_id","Source","Target","Type"],"isArrayAttr":{}},{"attributes":["Start","End","Strand","Id","Name","Phase","Score","Seq_id","Source","Target","Type"],"isArrayAttr":{}},{"attributes":["Start","End","Chunk"],"isArrayAttr":{"Sublist":1}}],"count":2,"lazyClass":4,"maxEnd":27133,"minStart":10240,"nclist":[[0,10240,12698,-1,"tig00002771.g105.t1.path1","tig00002771.g105.t1","tig00002771_overlapping_hits_sub_region","cannabis_loc_scaffold",[[1,10240,12698,-1,"100.0","tig00002771.g105.t1.mrna1","100.0","0","1518","0","tig00002771.g105.t1","tig00002771_overlapping_hits_sub_region","cannabis_loc_scaffold",[[2,12614,12698,-1,"tig00002771.g105.t1.mrna1.exon1","tig00002771.g105.t1",100,"tig00002771_overlapping_hits_sub_region","cannabis_loc_scaffold","tig00002771.g105.t1 1 84 +","exon"],[2,12388,12450,-1,"tig00002771.g105.t1.mrna1.exon2","tig00002771.g105.t1",100,"tig00002771_overlapping_hits_sub_region","cannabis_loc_scaffold","tig00002771.g105.t1 85 146 +","exon"],[2,12212,12255,-1,"tig00002771.g105.t1.mrna1.exon3","tig00002771.g105.t1",100,"tig00002771_overlapping_hits_sub_region","cannabis_loc_scaffold","tig00002771.g105.t1 147 189 +","exon"],[2,11928,11972,-1,"tig00002771.g105.t1.mrna1.exon4","tig00002771.g105.t1",100,"tig00002771_overlapping_hits_sub_region","cannabis_loc_scaffold","tig00002771.g105.t1 190 233 +","exon"],[2,11266,11609,-1,"tig00002771.g105.t1.mrna1.exon5","tig00002771.g105.t1",100,"tig00002771_overlapping_hits_sub_region","cannabis_loc_scaffold","tig00002771.g105.t1 234 576 +","exon"],[2,10240,11182,-1,"tig00002771.g105.t1.mrna1.exon6","tig00002771.g105.t1",100,"tig00002771_overlapping_hits_sub_region","cannabis_loc_scaffold","tig00002771.g105.t1 577 1518 +","exon"],[3,12614,12698,-1,"tig00002771.g105.t1.mrna1.cds1","tig00002771.g105.t1",0,100,"tig00002771_overlapping_hits_sub_region","cannabis_loc_scaffold","tig00002771.g105.t1 1 84 +","CDS"],[3,12388,12450,-1,"tig00002771.g105.t1.mrna1.cds2","tig00002771.g105.t1",0,100,"tig00002771_overlapping_hits_sub_region","cannabis_loc_scaffold","tig00002771.g105.t1 85 146 +","CDS"],[3,12212,12255,-1,"tig00002771.g105.t1.mrna1.cds3","tig00002771.g105.t1",2,100,"tig00002771_overlapping_hits_sub_region","cannabis_loc_scaffold","tig00002771.g105.t1 147 189 +","CDS"],[3,11928,11972,-1,"tig00002771.g105.t1.mrna1.cds4","tig00002771.g105.t1",0,100,"tig00002771_overlapping_hits_sub_region","cannabis_loc_scaffold","tig00002771.g105.t1 190 233 +","CDS"],[3,11266,11609,-1,"tig00002771.g105.t1.mrna1.cds5","tig00002771.g105.t1",2,100,"tig00002771_overlapping_hits_sub_region","cannabis_loc_scaffold","tig00002771.g105.t1 234 576 +","CDS"],[3,10240,11182,-1,"tig00002771.g105.t1.mrna1.cds6","tig00002771.g105.t1",0,100,"tig00002771_overlapping_hits_sub_region","cannabis_loc_scaffold","tig00002771.g105.t1 577 1518 +","CDS"]],"mRNA","0"]],"gene"],[0,25002,27133,-1,"tig00002771.g106.t1.path1","tig00002771.g106.t1","tig00002771_overlapping_hits_sub_region","cannabis_loc_scaffold",[[1,25002,27133,-1,"100.0","tig00002771.g106.t1.mrna1","100.0","0","1587","0","tig00002771.g106.t1","tig00002771_overlapping_hits_sub_region","cannabis_loc_scaffold",[[2,26589,27133,-1,"tig00002771.g106.t1.mrna1.exon1","tig00002771.g106.t1",100,"tig00002771_overlapping_hits_sub_region","cannabis_loc_scaffold","tig00002771.g106.t1 1 544 +","exon"],[2,26259,26344,-1,"tig00002771.g106.t1.mrna1.exon2","tig00002771.g106.t1",100,"tig00002771_overlapping_hits_sub_region","cannabis_loc_scaffold","tig00002771.g106.t1 545 629 +","exon"],[2,25999,26177,-1,"tig00002771.g106.t1.mrna1.exon3","tig00002771.g106.t1",100,"tig00002771_overlapping_hits_sub_region","cannabis_loc_scaffold","tig00002771.g106.t1 630 807 +","exon"],[2,25002,25782,-1,"tig00002771.g106.t1.mrna1.exon4","tig00002771.g106.t1",100,"tig00002771_overlapping_hits_sub_region","cannabis_loc_scaffold","tig00002771.g106.t1 808 1587 +","exon"],[3,26589,27133,-1,"tig00002771.g106.t1.mrna1.cds1","tig00002771.g106.t1",0,100,"tig00002771_overlapping_hits_sub_region","cannabis_loc_scaffold","tig00002771.g106.t1 1 544 +","CDS"],[3,26259,26344,-1,"tig00002771.g106.t1.mrna1.cds2","tig00002771.g106.t1",1,100,"tig00002771_overlapping_hits_sub_region","cannabis_loc_scaffold","tig00002771.g106.t1 545 629 +","CDS"],[3,25999,26177,-1,"tig00002771.g106.t1.mrna1.cds3","tig00002771.g106.t1",2,100,"tig00002771_overlapping_hits_sub_region","cannabis_loc_scaffold","tig00002771.g106.t1 630 807 +","CDS"],[3,25002,25782,-1,"tig00002771.g106.t1.mrna1.cds4","tig00002771.g106.t1",0,100,"tig00002771_overlapping_hits_sub_region","cannabis_loc_scaffold","tig00002771.g106.t1 808 1587 +","CDS"]],"mRNA","0"]],"gene"]],"urlTemplate":"lf-{Chunk}.json"}}