{"featureCount":6,"formatVersion":1,"histograms":{"meta":[{"arrayParams":{"chunkSize":10000,"length":2,"urlTemplate":"hist-50000-{Chunk}.json"},"basesPerBin":"50000"}],"stats":[{"basesPerBin":"50000","max":6,"mean":3.5}]},"intervals":{"classes":[{"attributes":["Start","End","Strand","Id","Name","Seq_id","Source","Subfeatures","Type"],"isArrayAttr":{"Subfeatures":1}},{"attributes":["Start","End","Strand","Coverage","Id","Identity","Indels","Matches","Mismatches","Name","Seq_id","Source","Subfeatures","Type","Unknowns"],"isArrayAttr":{"Subfeatures":1}},{"attributes":["Start","End","Strand","Id","Name","Score","Seq_id","Source","Target","Type"],"isArrayAttr":{}},{"attributes":["Start","End","Strand","Id","Name","Phase","Score","Seq_id","Source","Target","Type"],"isArrayAttr":{}},{"attributes":["Start","End","Chunk"],"isArrayAttr":{"Sublist":1}}],"count":6,"lazyClass":4,"maxEnd":50990,"minStart":7291,"nclist":[[0,7291,8288,-1,"tig00045978.g73.t1.path1","tig00045978.g73.t1","tig00045978_overlapping_hits_sub_region","cannabis_loc_scaffold",[[1,7291,8288,-1,"100.0","tig00045978.g73.t1.mrna1","100.0","0","798","0","tig00045978.g73.t1","tig00045978_overlapping_hits_sub_region","cannabis_loc_scaffold",[[2,8035,8288,-1,"tig00045978.g73.t1.mrna1.exon1","tig00045978.g73.t1",100,"tig00045978_overlapping_hits_sub_region","cannabis_loc_scaffold","tig00045978.g73.t1 1 253 +","exon"],[2,7642,7923,-1,"tig00045978.g73.t1.mrna1.exon2","tig00045978.g73.t1",100,"tig00045978_overlapping_hits_sub_region","cannabis_loc_scaffold","tig00045978.g73.t1 254 534 +","exon"],[2,7291,7555,-1,"tig00045978.g73.t1.mrna1.exon3","tig00045978.g73.t1",100,"tig00045978_overlapping_hits_sub_region","cannabis_loc_scaffold","tig00045978.g73.t1 535 798 +","exon"],[3,8035,8288,-1,"tig00045978.g73.t1.mrna1.cds1","tig00045978.g73.t1",0,100,"tig00045978_overlapping_hits_sub_region","cannabis_loc_scaffold","tig00045978.g73.t1 1 253 +","CDS"],[3,7642,7923,-1,"tig00045978.g73.t1.mrna1.cds2","tig00045978.g73.t1",1,100,"tig00045978_overlapping_hits_sub_region","cannabis_loc_scaffold","tig00045978.g73.t1 254 534 +","CDS"],[3,7291,7555,-1,"tig00045978.g73.t1.mrna1.cds3","tig00045978.g73.t1",0,100,"tig00045978_overlapping_hits_sub_region","cannabis_loc_scaffold","tig00045978.g73.t1 535 798 +","CDS"]],"mRNA","0"]],"gene"],[0,8757,11641,1,"tig00045978.g74.t1.path1","tig00045978.g74.t1","tig00045978_overlapping_hits_sub_region","cannabis_loc_scaffold",[[1,8757,11641,1,"100.0","tig00045978.g74.t1.mrna1","100.0","0","1023","0","tig00045978.g74.t1","tig00045978_overlapping_hits_sub_region","cannabis_loc_scaffold",[[2,8757,8878,1,"tig00045978.g74.t1.mrna1.exon1","tig00045978.g74.t1",100,"tig00045978_overlapping_hits_sub_region","cannabis_loc_scaffold","tig00045978.g74.t1 1 121 +","exon"],[2,9120,9212,1,"tig00045978.g74.t1.mrna1.exon2","tig00045978.g74.t1",100,"tig00045978_overlapping_hits_sub_region","cannabis_loc_scaffold","tig00045978.g74.t1 122 213 +","exon"],[2,9320,9413,1,"tig00045978.g74.t1.mrna1.exon3","tig00045978.g74.t1",100,"tig00045978_overlapping_hits_sub_region","cannabis_loc_scaffold","tig00045978.g74.t1 214 306 +","exon"],[2,10851,11536,1,"tig00045978.g74.t1.mrna1.exon4","tig00045978.g74.t1",100,"tig00045978_overlapping_hits_sub_region","cannabis_loc_scaffold","tig00045978.g74.t1 307 991 +","exon"],[2,11609,11641,1,"tig00045978.g74.t1.mrna1.exon5","tig00045978.g74.t1",100,"tig00045978_overlapping_hits_sub_region","cannabis_loc_scaffold","tig00045978.g74.t1 992 1023 +","exon"],[3,8757,8878,1,"tig00045978.g74.t1.mrna1.cds1","tig00045978.g74.t1",0,100,"tig00045978_overlapping_hits_sub_region","cannabis_loc_scaffold","tig00045978.g74.t1 1 121 +","CDS"],[3,9120,9212,1,"tig00045978.g74.t1.mrna1.cds2","tig00045978.g74.t1",1,100,"tig00045978_overlapping_hits_sub_region","cannabis_loc_scaffold","tig00045978.g74.t1 122 213 +","CDS"],[3,9320,9413,1,"tig00045978.g74.t1.mrna1.cds3","tig00045978.g74.t1",0,100,"tig00045978_overlapping_hits_sub_region","cannabis_loc_scaffold","tig00045978.g74.t1 214 306 +","CDS"],[3,10851,11536,1,"tig00045978.g74.t1.mrna1.cds4","tig00045978.g74.t1",0,100,"tig00045978_overlapping_hits_sub_region","cannabis_loc_scaffold","tig00045978.g74.t1 307 991 +","CDS"],[3,11609,11641,1,"tig00045978.g74.t1.mrna1.cds5","tig00045978.g74.t1",1,100,"tig00045978_overlapping_hits_sub_region","cannabis_loc_scaffold","tig00045978.g74.t1 992 1023 +","CDS"]],"mRNA","0"]],"gene"],[0,13136,14293,1,"tig00045978.g75.t1.path1","tig00045978.g75.t1","tig00045978_overlapping_hits_sub_region","cannabis_loc_scaffold",[[1,13136,14293,1,"100.0","tig00045978.g75.t1.mrna1","100.0","0","837","0","tig00045978.g75.t1","tig00045978_overlapping_hits_sub_region","cannabis_loc_scaffold",[[2,13136,13284,1,"tig00045978.g75.t1.mrna1.exon1","tig00045978.g75.t1",100,"tig00045978_overlapping_hits_sub_region","cannabis_loc_scaffold","tig00045978.g75.t1 1 148 +","exon"],[2,13365,13521,1,"tig00045978.g75.t1.mrna1.exon2","tig00045978.g75.t1",100,"tig00045978_overlapping_hits_sub_region","cannabis_loc_scaffold","tig00045978.g75.t1 149 304 +","exon"],[2,13602,13758,1,"tig00045978.g75.t1.mrna1.exon3","tig00045978.g75.t1",100,"tig00045978_overlapping_hits_sub_region","cannabis_loc_scaffold","tig00045978.g75.t1 305 460 +","exon"],[2,13916,14293,1,"tig00045978.g75.t1.mrna1.exon4","tig00045978.g75.t1",100,"tig00045978_overlapping_hits_sub_region","cannabis_loc_scaffold","tig00045978.g75.t1 461 837 +","exon"],[3,13136,13284,1,"tig00045978.g75.t1.mrna1.cds1","tig00045978.g75.t1",0,100,"tig00045978_overlapping_hits_sub_region","cannabis_loc_scaffold","tig00045978.g75.t1 1 148 +","CDS"],[3,13365,13521,1,"tig00045978.g75.t1.mrna1.cds2","tig00045978.g75.t1",1,100,"tig00045978_overlapping_hits_sub_region","cannabis_loc_scaffold","tig00045978.g75.t1 149 304 +","CDS"],[3,13602,13758,1,"tig00045978.g75.t1.mrna1.cds3","tig00045978.g75.t1",1,100,"tig00045978_overlapping_hits_sub_region","cannabis_loc_scaffold","tig00045978.g75.t1 305 460 +","CDS"],[3,13916,14293,1,"tig00045978.g75.t1.mrna1.cds4","tig00045978.g75.t1",1,100,"tig00045978_overlapping_hits_sub_region","cannabis_loc_scaffold","tig00045978.g75.t1 461 837 +","CDS"]],"mRNA","0"]],"gene"],[0,18848,22456,1,"tig00045978.g76.t1.path1","tig00045978.g76.t1","tig00045978_overlapping_hits_sub_region","cannabis_loc_scaffold",[[1,18848,22456,1,"100.0","tig00045978.g76.t1.mrna1","100.0","0","786","0","tig00045978.g76.t1","tig00045978_overlapping_hits_sub_region","cannabis_loc_scaffold",[[2,18848,18932,1,"tig00045978.g76.t1.mrna1.exon1","tig00045978.g76.t1",100,"tig00045978_overlapping_hits_sub_region","cannabis_loc_scaffold","tig00045978.g76.t1 1 84 +","exon"],[2,19017,19172,1,"tig00045978.g76.t1.mrna1.exon2","tig00045978.g76.t1",100,"tig00045978_overlapping_hits_sub_region","cannabis_loc_scaffold","tig00045978.g76.t1 85 239 +","exon"],[2,21043,21348,1,"tig00045978.g76.t1.mrna1.exon3","tig00045978.g76.t1",100,"tig00045978_overlapping_hits_sub_region","cannabis_loc_scaffold","tig00045978.g76.t1 240 544 +","exon"],[2,21473,21575,1,"tig00045978.g76.t1.mrna1.exon4","tig00045978.g76.t1",100,"tig00045978_overlapping_hits_sub_region","cannabis_loc_scaffold","tig00045978.g76.t1 545 646 +","exon"],[2,22201,22256,1,"tig00045978.g76.t1.mrna1.exon5","tig00045978.g76.t1",100,"tig00045978_overlapping_hits_sub_region","cannabis_loc_scaffold","tig00045978.g76.t1 647 701 +","exon"],[2,22371,22456,1,"tig00045978.g76.t1.mrna1.exon6","tig00045978.g76.t1",100,"tig00045978_overlapping_hits_sub_region","cannabis_loc_scaffold","tig00045978.g76.t1 702 786 +","exon"],[3,18848,18932,1,"tig00045978.g76.t1.mrna1.cds1","tig00045978.g76.t1",0,100,"tig00045978_overlapping_hits_sub_region","cannabis_loc_scaffold","tig00045978.g76.t1 1 84 +","CDS"],[3,19017,19172,1,"tig00045978.g76.t1.mrna1.cds2","tig00045978.g76.t1",0,100,"tig00045978_overlapping_hits_sub_region","cannabis_loc_scaffold","tig00045978.g76.t1 85 239 +","CDS"],[3,21043,21348,1,"tig00045978.g76.t1.mrna1.cds3","tig00045978.g76.t1",2,100,"tig00045978_overlapping_hits_sub_region","cannabis_loc_scaffold","tig00045978.g76.t1 240 544 +","CDS"],[3,21473,21575,1,"tig00045978.g76.t1.mrna1.cds4","tig00045978.g76.t1",1,100,"tig00045978_overlapping_hits_sub_region","cannabis_loc_scaffold","tig00045978.g76.t1 545 646 +","CDS"],[3,22201,22256,1,"tig00045978.g76.t1.mrna1.cds5","tig00045978.g76.t1",1,100,"tig00045978_overlapping_hits_sub_region","cannabis_loc_scaffold","tig00045978.g76.t1 647 701 +","CDS"],[3,22371,22456,1,"tig00045978.g76.t1.mrna1.cds6","tig00045978.g76.t1",2,100,"tig00045978_overlapping_hits_sub_region","cannabis_loc_scaffold","tig00045978.g76.t1 702 786 +","CDS"]],"mRNA","0"]],"gene"],[0,38229,41461,1,"tig00045978.g77.t1.path1","tig00045978.g77.t1","tig00045978_overlapping_hits_sub_region","cannabis_loc_scaffold",[[1,38229,41461,1,"100.0","tig00045978.g77.t1.mrna1","100.0","0","2250","0","tig00045978.g77.t1","tig00045978_overlapping_hits_sub_region","cannabis_loc_scaffold",[[2,38229,38425,1,"tig00045978.g77.t1.mrna1.exon1","tig00045978.g77.t1",100,"tig00045978_overlapping_hits_sub_region","cannabis_loc_scaffold","tig00045978.g77.t1 1 196 +","exon"],[2,38511,38663,1,"tig00045978.g77.t1.mrna1.exon2","tig00045978.g77.t1",100,"tig00045978_overlapping_hits_sub_region","cannabis_loc_scaffold","tig00045978.g77.t1 197 348 +","exon"],[2,38858,39233,1,"tig00045978.g77.t1.mrna1.exon3","tig00045978.g77.t1",100,"tig00045978_overlapping_hits_sub_region","cannabis_loc_scaffold","tig00045978.g77.t1 349 723 +","exon"],[2,39325,39412,1,"tig00045978.g77.t1.mrna1.exon4","tig00045978.g77.t1",100,"tig00045978_overlapping_hits_sub_region","cannabis_loc_scaffold","tig00045978.g77.t1 724 810 +","exon"],[2,39512,40085,1,"tig00045978.g77.t1.mrna1.exon5","tig00045978.g77.t1",100,"tig00045978_overlapping_hits_sub_region","cannabis_loc_scaffold","tig00045978.g77.t1 811 1383 +","exon"],[2,40352,40566,1,"tig00045978.g77.t1.mrna1.exon6","tig00045978.g77.t1",100,"tig00045978_overlapping_hits_sub_region","cannabis_loc_scaffold","tig00045978.g77.t1 1384 1597 +","exon"],[2,40685,40952,1,"tig00045978.g77.t1.mrna1.exon7","tig00045978.g77.t1",100,"tig00045978_overlapping_hits_sub_region","cannabis_loc_scaffold","tig00045978.g77.t1 1598 1864 +","exon"],[2,41075,41461,1,"tig00045978.g77.t1.mrna1.exon8","tig00045978.g77.t1",100,"tig00045978_overlapping_hits_sub_region","cannabis_loc_scaffold","tig00045978.g77.t1 1865 2250 +","exon"],[3,38229,38425,1,"tig00045978.g77.t1.mrna1.cds1","tig00045978.g77.t1",0,100,"tig00045978_overlapping_hits_sub_region","cannabis_loc_scaffold","tig00045978.g77.t1 1 196 +","CDS"],[3,38511,38663,1,"tig00045978.g77.t1.mrna1.cds2","tig00045978.g77.t1",1,100,"tig00045978_overlapping_hits_sub_region","cannabis_loc_scaffold","tig00045978.g77.t1 197 348 +","CDS"],[3,38858,39233,1,"tig00045978.g77.t1.mrna1.cds3","tig00045978.g77.t1",0,100,"tig00045978_overlapping_hits_sub_region","cannabis_loc_scaffold","tig00045978.g77.t1 349 723 +","CDS"],[3,39325,39412,1,"tig00045978.g77.t1.mrna1.cds4","tig00045978.g77.t1",0,100,"tig00045978_overlapping_hits_sub_region","cannabis_loc_scaffold","tig00045978.g77.t1 724 810 +","CDS"],[3,39512,40085,1,"tig00045978.g77.t1.mrna1.cds5","tig00045978.g77.t1",0,100,"tig00045978_overlapping_hits_sub_region","cannabis_loc_scaffold","tig00045978.g77.t1 811 1383 +","CDS"],[3,40352,40566,1,"tig00045978.g77.t1.mrna1.cds6","tig00045978.g77.t1",0,100,"tig00045978_overlapping_hits_sub_region","cannabis_loc_scaffold","tig00045978.g77.t1 1384 1597 +","CDS"],[3,40685,40952,1,"tig00045978.g77.t1.mrna1.cds7","tig00045978.g77.t1",1,100,"tig00045978_overlapping_hits_sub_region","cannabis_loc_scaffold","tig00045978.g77.t1 1598 1864 +","CDS"],[3,41075,41461,1,"tig00045978.g77.t1.mrna1.cds8","tig00045978.g77.t1",1,100,"tig00045978_overlapping_hits_sub_region","cannabis_loc_scaffold","tig00045978.g77.t1 1865 2250 +","CDS"]],"mRNA","0"]],"gene"],[0,42781,50990,-1,"tig00045978.g78.t1.path1","tig00045978.g78.t1","tig00045978_overlapping_hits_sub_region","cannabis_loc_scaffold",[[1,42781,50990,-1,"100.0","tig00045978.g78.t1.mrna1","100.0","0","5031","0","tig00045978.g78.t1","tig00045978_overlapping_hits_sub_region","cannabis_loc_scaffold",[[2,50936,50990,-1,"tig00045978.g78.t1.mrna1.exon1","tig00045978.g78.t1",100,"tig00045978_overlapping_hits_sub_region","cannabis_loc_scaffold","tig00045978.g78.t1 1 54 +","exon"],[2,50713,50782,-1,"tig00045978.g78.t1.mrna1.exon2","tig00045978.g78.t1",100,"tig00045978_overlapping_hits_sub_region","cannabis_loc_scaffold","tig00045978.g78.t1 55 123 +","exon"],[2,50368,50444,-1,"tig00045978.g78.t1.mrna1.exon3","tig00045978.g78.t1",100,"tig00045978_overlapping_hits_sub_region","cannabis_loc_scaffold","tig00045978.g78.t1 124 199 +","exon"],[2,50217,50268,-1,"tig00045978.g78.t1.mrna1.exon4","tig00045978.g78.t1",100,"tig00045978_overlapping_hits_sub_region","cannabis_loc_scaffold","tig00045978.g78.t1 200 250 +","exon"],[2,50095,50123,-1,"tig00045978.g78.t1.mrna1.exon5","tig00045978.g78.t1",100,"tig00045978_overlapping_hits_sub_region","cannabis_loc_scaffold","tig00045978.g78.t1 251 278 +","exon"],[2,49713,49782,-1,"tig00045978.g78.t1.mrna1.exon6","tig00045978.g78.t1",100,"tig00045978_overlapping_hits_sub_region","cannabis_loc_scaffold","tig00045978.g78.t1 279 347 +","exon"],[2,49092,49492,-1,"tig00045978.g78.t1.mrna1.exon7","tig00045978.g78.t1",100,"tig00045978_overlapping_hits_sub_region","cannabis_loc_scaffold","tig00045978.g78.t1 348 747 +","exon"],[2,48037,49013,-1,"tig00045978.g78.t1.mrna1.exon8","tig00045978.g78.t1",100,"tig00045978_overlapping_hits_sub_region","cannabis_loc_scaffold","tig00045978.g78.t1 748 1723 +","exon"],[2,45620,47876,-1,"tig00045978.g78.t1.mrna1.exon9","tig00045978.g78.t1",100,"tig00045978_overlapping_hits_sub_region","cannabis_loc_scaffold","tig00045978.g78.t1 1724 3979 +","exon"],[2,44870,45525,-1,"tig00045978.g78.t1.mrna1.exon10","tig00045978.g78.t1",100,"tig00045978_overlapping_hits_sub_region","cannabis_loc_scaffold","tig00045978.g78.t1 3980 4634 +","exon"],[2,43632,43801,-1,"tig00045978.g78.t1.mrna1.exon11","tig00045978.g78.t1",100,"tig00045978_overlapping_hits_sub_region","cannabis_loc_scaffold","tig00045978.g78.t1 4635 4803 +","exon"],[2,43399,43468,-1,"tig00045978.g78.t1.mrna1.exon12","tig00045978.g78.t1",100,"tig00045978_overlapping_hits_sub_region","cannabis_loc_scaffold","tig00045978.g78.t1 4804 4872 +","exon"],[2,43054,43130,-1,"tig00045978.g78.t1.mrna1.exon13","tig00045978.g78.t1",100,"tig00045978_overlapping_hits_sub_region","cannabis_loc_scaffold","tig00045978.g78.t1 4873 4948 +","exon"],[2,42908,42959,-1,"tig00045978.g78.t1.mrna1.exon14","tig00045978.g78.t1",100,"tig00045978_overlapping_hits_sub_region","cannabis_loc_scaffold","tig00045978.g78.t1 4949 4999 +","exon"],[2,42781,42813,-1,"tig00045978.g78.t1.mrna1.exon15","tig00045978.g78.t1",100,"tig00045978_overlapping_hits_sub_region","cannabis_loc_scaffold","tig00045978.g78.t1 5000 5031 +","exon"],[3,50936,50990,-1,"tig00045978.g78.t1.mrna1.cds1","tig00045978.g78.t1",0,100,"tig00045978_overlapping_hits_sub_region","cannabis_loc_scaffold","tig00045978.g78.t1 1 54 +","CDS"],[3,50713,50782,-1,"tig00045978.g78.t1.mrna1.cds2","tig00045978.g78.t1",0,100,"tig00045978_overlapping_hits_sub_region","cannabis_loc_scaffold","tig00045978.g78.t1 55 123 +","CDS"],[3,50368,50444,-1,"tig00045978.g78.t1.mrna1.cds3","tig00045978.g78.t1",0,100,"tig00045978_overlapping_hits_sub_region","cannabis_loc_scaffold","tig00045978.g78.t1 124 199 +","CDS"],[3,50217,50268,-1,"tig00045978.g78.t1.mrna1.cds4","tig00045978.g78.t1",1,100,"tig00045978_overlapping_hits_sub_region","cannabis_loc_scaffold","tig00045978.g78.t1 200 250 +","CDS"],[3,50095,50123,-1,"tig00045978.g78.t1.mrna1.cds5","tig00045978.g78.t1",1,100,"tig00045978_overlapping_hits_sub_region","cannabis_loc_scaffold","tig00045978.g78.t1 251 278 +","CDS"],[3,49713,49782,-1,"tig00045978.g78.t1.mrna1.cds6","tig00045978.g78.t1",2,100,"tig00045978_overlapping_hits_sub_region","cannabis_loc_scaffold","tig00045978.g78.t1 279 347 +","CDS"],[3,49092,49492,-1,"tig00045978.g78.t1.mrna1.cds7","tig00045978.g78.t1",2,100,"tig00045978_overlapping_hits_sub_region","cannabis_loc_scaffold","tig00045978.g78.t1 348 747 +","CDS"],[3,48037,49013,-1,"tig00045978.g78.t1.mrna1.cds8","tig00045978.g78.t1",0,100,"tig00045978_overlapping_hits_sub_region","cannabis_loc_scaffold","tig00045978.g78.t1 748 1723 +","CDS"],[3,45620,47876,-1,"tig00045978.g78.t1.mrna1.cds9","tig00045978.g78.t1",1,100,"tig00045978_overlapping_hits_sub_region","cannabis_loc_scaffold","tig00045978.g78.t1 1724 3979 +","CDS"],[3,44870,45525,-1,"tig00045978.g78.t1.mrna1.cds10","tig00045978.g78.t1",1,100,"tig00045978_overlapping_hits_sub_region","cannabis_loc_scaffold","tig00045978.g78.t1 3980 4634 +","CDS"],[3,43632,43801,-1,"tig00045978.g78.t1.mrna1.cds11","tig00045978.g78.t1",2,100,"tig00045978_overlapping_hits_sub_region","cannabis_loc_scaffold","tig00045978.g78.t1 4635 4803 +","CDS"],[3,43399,43468,-1,"tig00045978.g78.t1.mrna1.cds12","tig00045978.g78.t1",0,100,"tig00045978_overlapping_hits_sub_region","cannabis_loc_scaffold","tig00045978.g78.t1 4804 4872 +","CDS"],[3,43054,43130,-1,"tig00045978.g78.t1.mrna1.cds13","tig00045978.g78.t1",0,100,"tig00045978_overlapping_hits_sub_region","cannabis_loc_scaffold","tig00045978.g78.t1 4873 4948 +","CDS"],[3,42908,42959,-1,"tig00045978.g78.t1.mrna1.cds14","tig00045978.g78.t1",1,100,"tig00045978_overlapping_hits_sub_region","cannabis_loc_scaffold","tig00045978.g78.t1 4949 4999 +","CDS"],[3,42781,42813,-1,"tig00045978.g78.t1.mrna1.cds15","tig00045978.g78.t1",1,100,"tig00045978_overlapping_hits_sub_region","cannabis_loc_scaffold","tig00045978.g78.t1 5000 5031 +","CDS"]],"mRNA","0"]],"gene"]],"urlTemplate":"lf-{Chunk}.json"}}