{"featureCount":5,"formatVersion":1,"histograms":{"meta":[{"arrayParams":{"chunkSize":10000,"length":2,"urlTemplate":"hist-20000-{Chunk}.json"},"basesPerBin":"20000"}],"stats":[{"basesPerBin":"20000","max":3,"mean":2.5}]},"intervals":{"classes":[{"attributes":["Start","End","Strand","Id","Name","Seq_id","Source","Subfeatures","Type"],"isArrayAttr":{"Subfeatures":1}},{"attributes":["Start","End","Strand","Coverage","Id","Identity","Indels","Matches","Mismatches","Name","Seq_id","Source","Subfeatures","Type","Unknowns"],"isArrayAttr":{"Subfeatures":1}},{"attributes":["Start","End","Strand","Id","Name","Score","Seq_id","Source","Target","Type"],"isArrayAttr":{}},{"attributes":["Start","End","Strand","Id","Name","Phase","Score","Seq_id","Source","Target","Type"],"isArrayAttr":{}},{"attributes":["Start","End","Chunk"],"isArrayAttr":{"Sublist":1}}],"count":5,"lazyClass":4,"maxEnd":30723,"minStart":176,"nclist":[[0,176,3377,-1,"tig00436138.g124.t1.path1","tig00436138.g124.t1","tig00436138_overlapping_hits_sub_region","cannabis_loc_scaffold",[[1,176,3377,-1,"100.0","tig00436138.g124.t1.mrna1","100.0","0","1158","0","tig00436138.g124.t1","tig00436138_overlapping_hits_sub_region","cannabis_loc_scaffold",[[2,3299,3377,-1,"tig00436138.g124.t1.mrna1.exon1","tig00436138.g124.t1",100,"tig00436138_overlapping_hits_sub_region","cannabis_loc_scaffold","tig00436138.g124.t1 1 78 +","exon"],[2,2278,2423,-1,"tig00436138.g124.t1.mrna1.exon2","tig00436138.g124.t1",100,"tig00436138_overlapping_hits_sub_region","cannabis_loc_scaffold","tig00436138.g124.t1 79 223 +","exon"],[2,1504,1597,-1,"tig00436138.g124.t1.mrna1.exon3","tig00436138.g124.t1",100,"tig00436138_overlapping_hits_sub_region","cannabis_loc_scaffold","tig00436138.g124.t1 224 316 +","exon"],[2,1288,1417,-1,"tig00436138.g124.t1.mrna1.exon4","tig00436138.g124.t1",100,"tig00436138_overlapping_hits_sub_region","cannabis_loc_scaffold","tig00436138.g124.t1 317 445 +","exon"],[2,927,1135,-1,"tig00436138.g124.t1.mrna1.exon5","tig00436138.g124.t1",100,"tig00436138_overlapping_hits_sub_region","cannabis_loc_scaffold","tig00436138.g124.t1 446 653 +","exon"],[2,644,844,-1,"tig00436138.g124.t1.mrna1.exon6","tig00436138.g124.t1",100,"tig00436138_overlapping_hits_sub_region","cannabis_loc_scaffold","tig00436138.g124.t1 654 853 +","exon"],[2,360,567,-1,"tig00436138.g124.t1.mrna1.exon7","tig00436138.g124.t1",100,"tig00436138_overlapping_hits_sub_region","cannabis_loc_scaffold","tig00436138.g124.t1 854 1060 +","exon"],[2,176,274,-1,"tig00436138.g124.t1.mrna1.exon8","tig00436138.g124.t1",100,"tig00436138_overlapping_hits_sub_region","cannabis_loc_scaffold","tig00436138.g124.t1 1061 1158 +","exon"],[3,3299,3377,-1,"tig00436138.g124.t1.mrna1.cds1","tig00436138.g124.t1",0,100,"tig00436138_overlapping_hits_sub_region","cannabis_loc_scaffold","tig00436138.g124.t1 1 78 +","CDS"],[3,2278,2423,-1,"tig00436138.g124.t1.mrna1.cds2","tig00436138.g124.t1",0,100,"tig00436138_overlapping_hits_sub_region","cannabis_loc_scaffold","tig00436138.g124.t1 79 223 +","CDS"],[3,1504,1597,-1,"tig00436138.g124.t1.mrna1.cds3","tig00436138.g124.t1",1,100,"tig00436138_overlapping_hits_sub_region","cannabis_loc_scaffold","tig00436138.g124.t1 224 316 +","CDS"],[3,1288,1417,-1,"tig00436138.g124.t1.mrna1.cds4","tig00436138.g124.t1",1,100,"tig00436138_overlapping_hits_sub_region","cannabis_loc_scaffold","tig00436138.g124.t1 317 445 +","CDS"],[3,927,1135,-1,"tig00436138.g124.t1.mrna1.cds5","tig00436138.g124.t1",1,100,"tig00436138_overlapping_hits_sub_region","cannabis_loc_scaffold","tig00436138.g124.t1 446 653 +","CDS"],[3,644,844,-1,"tig00436138.g124.t1.mrna1.cds6","tig00436138.g124.t1",2,100,"tig00436138_overlapping_hits_sub_region","cannabis_loc_scaffold","tig00436138.g124.t1 654 853 +","CDS"],[3,360,567,-1,"tig00436138.g124.t1.mrna1.cds7","tig00436138.g124.t1",1,100,"tig00436138_overlapping_hits_sub_region","cannabis_loc_scaffold","tig00436138.g124.t1 854 1060 +","CDS"],[3,176,274,-1,"tig00436138.g124.t1.mrna1.cds8","tig00436138.g124.t1",1,100,"tig00436138_overlapping_hits_sub_region","cannabis_loc_scaffold","tig00436138.g124.t1 1061 1158 +","CDS"]],"mRNA","0"]],"gene"],[0,13915,15238,-1,"tig00436138.g123.t1.path1","tig00436138.g123.t1","tig00436138_overlapping_hits_sub_region","cannabis_loc_scaffold",[[1,13915,15238,-1,"100.0","tig00436138.g123.t1.mrna1","100.0","0","525","0","tig00436138.g123.t1","tig00436138_overlapping_hits_sub_region","cannabis_loc_scaffold",[[2,15197,15238,-1,"tig00436138.g123.t1.mrna1.exon1","tig00436138.g123.t1",100,"tig00436138_overlapping_hits_sub_region","cannabis_loc_scaffold","tig00436138.g123.t1 1 41 +","exon"],[2,14847,15040,-1,"tig00436138.g123.t1.mrna1.exon2","tig00436138.g123.t1",100,"tig00436138_overlapping_hits_sub_region","cannabis_loc_scaffold","tig00436138.g123.t1 42 234 +","exon"],[2,14652,14734,-1,"tig00436138.g123.t1.mrna1.exon3","tig00436138.g123.t1",100,"tig00436138_overlapping_hits_sub_region","cannabis_loc_scaffold","tig00436138.g123.t1 235 316 +","exon"],[2,13915,14124,-1,"tig00436138.g123.t1.mrna1.exon4","tig00436138.g123.t1",100,"tig00436138_overlapping_hits_sub_region","cannabis_loc_scaffold","tig00436138.g123.t1 317 525 +","exon"],[3,15197,15238,-1,"tig00436138.g123.t1.mrna1.cds1","tig00436138.g123.t1",0,100,"tig00436138_overlapping_hits_sub_region","cannabis_loc_scaffold","tig00436138.g123.t1 1 41 +","CDS"],[3,14847,15040,-1,"tig00436138.g123.t1.mrna1.cds2","tig00436138.g123.t1",2,100,"tig00436138_overlapping_hits_sub_region","cannabis_loc_scaffold","tig00436138.g123.t1 42 234 +","CDS"],[3,14652,14734,-1,"tig00436138.g123.t1.mrna1.cds3","tig00436138.g123.t1",0,100,"tig00436138_overlapping_hits_sub_region","cannabis_loc_scaffold","tig00436138.g123.t1 235 316 +","CDS"],[3,13915,14124,-1,"tig00436138.g123.t1.mrna1.cds4","tig00436138.g123.t1",1,100,"tig00436138_overlapping_hits_sub_region","cannabis_loc_scaffold","tig00436138.g123.t1 317 525 +","CDS"]],"mRNA","0"]],"gene"],[0,20729,22466,1,"tig00436138.g122.t1.path1","tig00436138.g122.t1","tig00436138_overlapping_hits_sub_region","cannabis_loc_scaffold",[[1,20729,22466,1,"100.0","tig00436138.g122.t1.mrna1","100.0","0","693","0","tig00436138.g122.t1","tig00436138_overlapping_hits_sub_region","cannabis_loc_scaffold",[[2,20729,20741,1,"tig00436138.g122.t1.mrna1.exon1","tig00436138.g122.t1",100,"tig00436138_overlapping_hits_sub_region","cannabis_loc_scaffold","tig00436138.g122.t1 1 12 +","exon"],[2,20892,20956,1,"tig00436138.g122.t1.mrna1.exon2","tig00436138.g122.t1",100,"tig00436138_overlapping_hits_sub_region","cannabis_loc_scaffold","tig00436138.g122.t1 13 76 +","exon"],[2,21269,21576,1,"tig00436138.g122.t1.mrna1.exon3","tig00436138.g122.t1",100,"tig00436138_overlapping_hits_sub_region","cannabis_loc_scaffold","tig00436138.g122.t1 77 383 +","exon"],[2,21735,21996,1,"tig00436138.g122.t1.mrna1.exon4","tig00436138.g122.t1",100,"tig00436138_overlapping_hits_sub_region","cannabis_loc_scaffold","tig00436138.g122.t1 384 644 +","exon"],[2,22417,22466,1,"tig00436138.g122.t1.mrna1.exon5","tig00436138.g122.t1",100,"tig00436138_overlapping_hits_sub_region","cannabis_loc_scaffold","tig00436138.g122.t1 645 693 +","exon"],[3,20729,20741,1,"tig00436138.g122.t1.mrna1.cds1","tig00436138.g122.t1",0,100,"tig00436138_overlapping_hits_sub_region","cannabis_loc_scaffold","tig00436138.g122.t1 1 12 +","CDS"],[3,20892,20956,1,"tig00436138.g122.t1.mrna1.cds2","tig00436138.g122.t1",0,100,"tig00436138_overlapping_hits_sub_region","cannabis_loc_scaffold","tig00436138.g122.t1 13 76 +","CDS"],[3,21269,21576,1,"tig00436138.g122.t1.mrna1.cds3","tig00436138.g122.t1",1,100,"tig00436138_overlapping_hits_sub_region","cannabis_loc_scaffold","tig00436138.g122.t1 77 383 +","CDS"],[3,21735,21996,1,"tig00436138.g122.t1.mrna1.cds4","tig00436138.g122.t1",2,100,"tig00436138_overlapping_hits_sub_region","cannabis_loc_scaffold","tig00436138.g122.t1 384 644 +","CDS"],[3,22417,22466,1,"tig00436138.g122.t1.mrna1.cds5","tig00436138.g122.t1",2,100,"tig00436138_overlapping_hits_sub_region","cannabis_loc_scaffold","tig00436138.g122.t1 645 693 +","CDS"]],"mRNA","0"]],"gene"],[0,25446,27006,1,"tig00436138.g121.t1.path1","tig00436138.g121.t1","tig00436138_overlapping_hits_sub_region","cannabis_loc_scaffold",[[1,25446,27006,1,"100.0","tig00436138.g121.t1.mrna1","100.0","0","1170","0","tig00436138.g121.t1","tig00436138_overlapping_hits_sub_region","cannabis_loc_scaffold",[[2,25446,25544,1,"tig00436138.g121.t1.mrna1.exon1","tig00436138.g121.t1",100,"tig00436138_overlapping_hits_sub_region","cannabis_loc_scaffold","tig00436138.g121.t1 1 98 +","exon"],[2,25755,26303,1,"tig00436138.g121.t1.mrna1.exon2","tig00436138.g121.t1",100,"tig00436138_overlapping_hits_sub_region","cannabis_loc_scaffold","tig00436138.g121.t1 99 646 +","exon"],[2,26402,26713,1,"tig00436138.g121.t1.mrna1.exon3","tig00436138.g121.t1",100,"tig00436138_overlapping_hits_sub_region","cannabis_loc_scaffold","tig00436138.g121.t1 647 957 +","exon"],[2,26793,27006,1,"tig00436138.g121.t1.mrna1.exon4","tig00436138.g121.t1",100,"tig00436138_overlapping_hits_sub_region","cannabis_loc_scaffold","tig00436138.g121.t1 958 1170 +","exon"],[3,25446,25544,1,"tig00436138.g121.t1.mrna1.cds1","tig00436138.g121.t1",0,100,"tig00436138_overlapping_hits_sub_region","cannabis_loc_scaffold","tig00436138.g121.t1 1 98 +","CDS"],[3,25755,26303,1,"tig00436138.g121.t1.mrna1.cds2","tig00436138.g121.t1",2,100,"tig00436138_overlapping_hits_sub_region","cannabis_loc_scaffold","tig00436138.g121.t1 99 646 +","CDS"],[3,26402,26713,1,"tig00436138.g121.t1.mrna1.cds3","tig00436138.g121.t1",1,100,"tig00436138_overlapping_hits_sub_region","cannabis_loc_scaffold","tig00436138.g121.t1 647 957 +","CDS"],[3,26793,27006,1,"tig00436138.g121.t1.mrna1.cds4","tig00436138.g121.t1",0,100,"tig00436138_overlapping_hits_sub_region","cannabis_loc_scaffold","tig00436138.g121.t1 958 1170 +","CDS"]],"mRNA","0"]],"gene"],[0,28688,30723,1,"tig00436138.g120.t1.path1","tig00436138.g120.t1","tig00436138_overlapping_hits_sub_region","cannabis_loc_scaffold",[[1,28688,30723,1,"100.0","tig00436138.g120.t1.mrna1","100.0","0","1197","0","tig00436138.g120.t1","tig00436138_overlapping_hits_sub_region","cannabis_loc_scaffold",[[2,28688,29299,1,"tig00436138.g120.t1.mrna1.exon1","tig00436138.g120.t1",100,"tig00436138_overlapping_hits_sub_region","cannabis_loc_scaffold","tig00436138.g120.t1 1 611 +","exon"],[2,29766,30076,1,"tig00436138.g120.t1.mrna1.exon2","tig00436138.g120.t1",100,"tig00436138_overlapping_hits_sub_region","cannabis_loc_scaffold","tig00436138.g120.t1 612 921 +","exon"],[2,30269,30324,1,"tig00436138.g120.t1.mrna1.exon3","tig00436138.g120.t1",100,"tig00436138_overlapping_hits_sub_region","cannabis_loc_scaffold","tig00436138.g120.t1 922 976 +","exon"],[2,30502,30723,1,"tig00436138.g120.t1.mrna1.exon4","tig00436138.g120.t1",100,"tig00436138_overlapping_hits_sub_region","cannabis_loc_scaffold","tig00436138.g120.t1 977 1197 +","exon"],[3,28688,29299,1,"tig00436138.g120.t1.mrna1.cds1","tig00436138.g120.t1",0,100,"tig00436138_overlapping_hits_sub_region","cannabis_loc_scaffold","tig00436138.g120.t1 1 611 +","CDS"],[3,29766,30076,1,"tig00436138.g120.t1.mrna1.cds2","tig00436138.g120.t1",2,100,"tig00436138_overlapping_hits_sub_region","cannabis_loc_scaffold","tig00436138.g120.t1 612 921 +","CDS"],[3,30269,30324,1,"tig00436138.g120.t1.mrna1.cds3","tig00436138.g120.t1",0,100,"tig00436138_overlapping_hits_sub_region","cannabis_loc_scaffold","tig00436138.g120.t1 922 976 +","CDS"],[3,30502,30723,1,"tig00436138.g120.t1.mrna1.cds4","tig00436138.g120.t1",1,100,"tig00436138_overlapping_hits_sub_region","cannabis_loc_scaffold","tig00436138.g120.t1 977 1197 +","CDS"]],"mRNA","0"]],"gene"]],"urlTemplate":"lf-{Chunk}.json"}}