{"featureCount":6,"formatVersion":1,"histograms":{"meta":[{"arrayParams":{"chunkSize":10000,"length":2,"urlTemplate":"hist-20000-{Chunk}.json"},"basesPerBin":"20000"}],"stats":[{"basesPerBin":"20000","max":4,"mean":3.5}]},"intervals":{"classes":[{"attributes":["Start","End","Strand","Id","Name","Seq_id","Source","Subfeatures","Type"],"isArrayAttr":{"Subfeatures":1}},{"attributes":["Start","End","Strand","Coverage","Id","Identity","Indels","Matches","Mismatches","Name","Seq_id","Source","Subfeatures","Type","Unknowns"],"isArrayAttr":{"Subfeatures":1}},{"attributes":["Start","End","Strand","Id","Name","Score","Seq_id","Source","Target","Type"],"isArrayAttr":{}},{"attributes":["Start","End","Strand","Id","Name","Phase","Score","Seq_id","Source","Target","Type"],"isArrayAttr":{}},{"attributes":["Start","End","Chunk"],"isArrayAttr":{"Sublist":1}}],"count":6,"lazyClass":4,"maxEnd":38871,"minStart":181,"nclist":[[0,181,4724,1,"tig00006085.g25.t1.path1","tig00006085.g25.t1","tig00006085_overlapping_hits_sub_region","cannabis_loc_scaffold",[[1,181,4724,1,"100.0","tig00006085.g25.t1.mrna1","100.0","0","2961","0","tig00006085.g25.t1","tig00006085_overlapping_hits_sub_region","cannabis_loc_scaffold",[[2,181,232,1,"tig00006085.g25.t1.mrna1.exon1","tig00006085.g25.t1",100,"tig00006085_overlapping_hits_sub_region","cannabis_loc_scaffold","tig00006085.g25.t1 1 51 +","exon"],[2,436,796,1,"tig00006085.g25.t1.mrna1.exon2","tig00006085.g25.t1",100,"tig00006085_overlapping_hits_sub_region","cannabis_loc_scaffold","tig00006085.g25.t1 52 411 +","exon"],[2,877,1180,1,"tig00006085.g25.t1.mrna1.exon3","tig00006085.g25.t1",100,"tig00006085_overlapping_hits_sub_region","cannabis_loc_scaffold","tig00006085.g25.t1 412 714 +","exon"],[2,1264,1535,1,"tig00006085.g25.t1.mrna1.exon4","tig00006085.g25.t1",100,"tig00006085_overlapping_hits_sub_region","cannabis_loc_scaffold","tig00006085.g25.t1 715 985 +","exon"],[2,1634,1756,1,"tig00006085.g25.t1.mrna1.exon5","tig00006085.g25.t1",100,"tig00006085_overlapping_hits_sub_region","cannabis_loc_scaffold","tig00006085.g25.t1 986 1107 +","exon"],[2,2065,2244,1,"tig00006085.g25.t1.mrna1.exon6","tig00006085.g25.t1",100,"tig00006085_overlapping_hits_sub_region","cannabis_loc_scaffold","tig00006085.g25.t1 1108 1286 +","exon"],[2,2333,2400,1,"tig00006085.g25.t1.mrna1.exon7","tig00006085.g25.t1",100,"tig00006085_overlapping_hits_sub_region","cannabis_loc_scaffold","tig00006085.g25.t1 1287 1353 +","exon"],[2,2564,2655,1,"tig00006085.g25.t1.mrna1.exon8","tig00006085.g25.t1",100,"tig00006085_overlapping_hits_sub_region","cannabis_loc_scaffold","tig00006085.g25.t1 1354 1444 +","exon"],[2,2722,2928,1,"tig00006085.g25.t1.mrna1.exon9","tig00006085.g25.t1",100,"tig00006085_overlapping_hits_sub_region","cannabis_loc_scaffold","tig00006085.g25.t1 1445 1650 +","exon"],[2,3204,3735,1,"tig00006085.g25.t1.mrna1.exon10","tig00006085.g25.t1",100,"tig00006085_overlapping_hits_sub_region","cannabis_loc_scaffold","tig00006085.g25.t1 1651 2181 +","exon"],[2,3944,4724,1,"tig00006085.g25.t1.mrna1.exon11","tig00006085.g25.t1",100,"tig00006085_overlapping_hits_sub_region","cannabis_loc_scaffold","tig00006085.g25.t1 2182 2961 +","exon"],[3,181,232,1,"tig00006085.g25.t1.mrna1.cds1","tig00006085.g25.t1",0,100,"tig00006085_overlapping_hits_sub_region","cannabis_loc_scaffold","tig00006085.g25.t1 1 51 +","CDS"],[3,436,796,1,"tig00006085.g25.t1.mrna1.cds2","tig00006085.g25.t1",0,100,"tig00006085_overlapping_hits_sub_region","cannabis_loc_scaffold","tig00006085.g25.t1 52 411 +","CDS"],[3,877,1180,1,"tig00006085.g25.t1.mrna1.cds3","tig00006085.g25.t1",0,100,"tig00006085_overlapping_hits_sub_region","cannabis_loc_scaffold","tig00006085.g25.t1 412 714 +","CDS"],[3,1264,1535,1,"tig00006085.g25.t1.mrna1.cds4","tig00006085.g25.t1",0,100,"tig00006085_overlapping_hits_sub_region","cannabis_loc_scaffold","tig00006085.g25.t1 715 985 +","CDS"],[3,1634,1756,1,"tig00006085.g25.t1.mrna1.cds5","tig00006085.g25.t1",1,100,"tig00006085_overlapping_hits_sub_region","cannabis_loc_scaffold","tig00006085.g25.t1 986 1107 +","CDS"],[3,2065,2244,1,"tig00006085.g25.t1.mrna1.cds6","tig00006085.g25.t1",0,100,"tig00006085_overlapping_hits_sub_region","cannabis_loc_scaffold","tig00006085.g25.t1 1108 1286 +","CDS"],[3,2333,2400,1,"tig00006085.g25.t1.mrna1.cds7","tig00006085.g25.t1",2,100,"tig00006085_overlapping_hits_sub_region","cannabis_loc_scaffold","tig00006085.g25.t1 1287 1353 +","CDS"],[3,2564,2655,1,"tig00006085.g25.t1.mrna1.cds8","tig00006085.g25.t1",0,100,"tig00006085_overlapping_hits_sub_region","cannabis_loc_scaffold","tig00006085.g25.t1 1354 1444 +","CDS"],[3,2722,2928,1,"tig00006085.g25.t1.mrna1.cds9","tig00006085.g25.t1",1,100,"tig00006085_overlapping_hits_sub_region","cannabis_loc_scaffold","tig00006085.g25.t1 1445 1650 +","CDS"],[3,3204,3735,1,"tig00006085.g25.t1.mrna1.cds10","tig00006085.g25.t1",0,100,"tig00006085_overlapping_hits_sub_region","cannabis_loc_scaffold","tig00006085.g25.t1 1651 2181 +","CDS"],[3,3944,4724,1,"tig00006085.g25.t1.mrna1.cds11","tig00006085.g25.t1",0,100,"tig00006085_overlapping_hits_sub_region","cannabis_loc_scaffold","tig00006085.g25.t1 2182 2961 +","CDS"]],"mRNA","0"]],"gene"],[0,7781,9627,-1,"tig00006085.g26.t1.path1","tig00006085.g26.t1","tig00006085_overlapping_hits_sub_region","cannabis_loc_scaffold",[[1,7781,9627,-1,"100.0","tig00006085.g26.t1.mrna1","100.0","0","1374","0","tig00006085.g26.t1","tig00006085_overlapping_hits_sub_region","cannabis_loc_scaffold",[[2,9011,9627,-1,"tig00006085.g26.t1.mrna1.exon1","tig00006085.g26.t1",100,"tig00006085_overlapping_hits_sub_region","cannabis_loc_scaffold","tig00006085.g26.t1 1 616 +","exon"],[2,8685,8913,-1,"tig00006085.g26.t1.mrna1.exon2","tig00006085.g26.t1",100,"tig00006085_overlapping_hits_sub_region","cannabis_loc_scaffold","tig00006085.g26.t1 617 844 +","exon"],[2,8498,8563,-1,"tig00006085.g26.t1.mrna1.exon3","tig00006085.g26.t1",100,"tig00006085_overlapping_hits_sub_region","cannabis_loc_scaffold","tig00006085.g26.t1 845 909 +","exon"],[2,8054,8370,-1,"tig00006085.g26.t1.mrna1.exon4","tig00006085.g26.t1",100,"tig00006085_overlapping_hits_sub_region","cannabis_loc_scaffold","tig00006085.g26.t1 910 1225 +","exon"],[2,7781,7930,-1,"tig00006085.g26.t1.mrna1.exon5","tig00006085.g26.t1",100,"tig00006085_overlapping_hits_sub_region","cannabis_loc_scaffold","tig00006085.g26.t1 1226 1374 +","exon"],[3,9011,9627,-1,"tig00006085.g26.t1.mrna1.cds1","tig00006085.g26.t1",0,100,"tig00006085_overlapping_hits_sub_region","cannabis_loc_scaffold","tig00006085.g26.t1 1 616 +","CDS"],[3,8685,8913,-1,"tig00006085.g26.t1.mrna1.cds2","tig00006085.g26.t1",1,100,"tig00006085_overlapping_hits_sub_region","cannabis_loc_scaffold","tig00006085.g26.t1 617 844 +","CDS"],[3,8498,8563,-1,"tig00006085.g26.t1.mrna1.cds3","tig00006085.g26.t1",1,100,"tig00006085_overlapping_hits_sub_region","cannabis_loc_scaffold","tig00006085.g26.t1 845 909 +","CDS"],[3,8054,8370,-1,"tig00006085.g26.t1.mrna1.cds4","tig00006085.g26.t1",0,100,"tig00006085_overlapping_hits_sub_region","cannabis_loc_scaffold","tig00006085.g26.t1 910 1225 +","CDS"],[3,7781,7930,-1,"tig00006085.g26.t1.mrna1.cds5","tig00006085.g26.t1",1,100,"tig00006085_overlapping_hits_sub_region","cannabis_loc_scaffold","tig00006085.g26.t1 1226 1374 +","CDS"]],"mRNA","0"]],"gene"],[0,18728,20217,1,"tig00006085.g27.t1.path1","tig00006085.g27.t1","tig00006085_overlapping_hits_sub_region","cannabis_loc_scaffold",[[1,18728,20217,1,"99.7","tig00006085.g27.t1.mrna1","100.0","0","730","0","tig00006085.g27.t1","tig00006085_overlapping_hits_sub_region","cannabis_loc_scaffold",[[2,18728,18810,1,"tig00006085.g27.t1.mrna1.exon1","tig00006085.g27.t1",100,"tig00006085_overlapping_hits_sub_region","cannabis_loc_scaffold","tig00006085.g27.t1 3 84 +","exon"],[2,19041,19126,1,"tig00006085.g27.t1.mrna1.exon2","tig00006085.g27.t1",100,"tig00006085_overlapping_hits_sub_region","cannabis_loc_scaffold","tig00006085.g27.t1 85 169 +","exon"],[2,19210,19290,1,"tig00006085.g27.t1.mrna1.exon3","tig00006085.g27.t1",100,"tig00006085_overlapping_hits_sub_region","cannabis_loc_scaffold","tig00006085.g27.t1 170 249 +","exon"],[2,19386,19502,1,"tig00006085.g27.t1.mrna1.exon4","tig00006085.g27.t1",100,"tig00006085_overlapping_hits_sub_region","cannabis_loc_scaffold","tig00006085.g27.t1 250 365 +","exon"],[2,19710,19771,1,"tig00006085.g27.t1.mrna1.exon5","tig00006085.g27.t1",100,"tig00006085_overlapping_hits_sub_region","cannabis_loc_scaffold","tig00006085.g27.t1 366 426 +","exon"],[2,19839,19939,1,"tig00006085.g27.t1.mrna1.exon6","tig00006085.g27.t1",100,"tig00006085_overlapping_hits_sub_region","cannabis_loc_scaffold","tig00006085.g27.t1 427 526 +","exon"],[2,20011,20217,1,"tig00006085.g27.t1.mrna1.exon7","tig00006085.g27.t1",100,"tig00006085_overlapping_hits_sub_region","cannabis_loc_scaffold","tig00006085.g27.t1 527 732 +","exon"],[3,18729,18810,1,"tig00006085.g27.t1.mrna1.cds1","tig00006085.g27.t1",0,100,"tig00006085_overlapping_hits_sub_region","cannabis_loc_scaffold","tig00006085.g27.t1 4 84 +","CDS"],[3,19041,19126,1,"tig00006085.g27.t1.mrna1.cds2","tig00006085.g27.t1",0,100,"tig00006085_overlapping_hits_sub_region","cannabis_loc_scaffold","tig00006085.g27.t1 85 169 +","CDS"],[3,19210,19290,1,"tig00006085.g27.t1.mrna1.cds3","tig00006085.g27.t1",1,100,"tig00006085_overlapping_hits_sub_region","cannabis_loc_scaffold","tig00006085.g27.t1 170 249 +","CDS"],[3,19386,19502,1,"tig00006085.g27.t1.mrna1.cds4","tig00006085.g27.t1",0,100,"tig00006085_overlapping_hits_sub_region","cannabis_loc_scaffold","tig00006085.g27.t1 250 365 +","CDS"],[3,19710,19771,1,"tig00006085.g27.t1.mrna1.cds5","tig00006085.g27.t1",2,100,"tig00006085_overlapping_hits_sub_region","cannabis_loc_scaffold","tig00006085.g27.t1 366 426 +","CDS"],[3,19839,19939,1,"tig00006085.g27.t1.mrna1.cds6","tig00006085.g27.t1",0,100,"tig00006085_overlapping_hits_sub_region","cannabis_loc_scaffold","tig00006085.g27.t1 427 526 +","CDS"],[3,20011,20217,1,"tig00006085.g27.t1.mrna1.cds7","tig00006085.g27.t1",1,100,"tig00006085_overlapping_hits_sub_region","cannabis_loc_scaffold","tig00006085.g27.t1 527 732 +","CDS"]],"mRNA","0"]],"gene"],[0,21642,22444,1,"tig00006085.g28.t1.path1","tig00006085.g28.t1","tig00006085_overlapping_hits_sub_region","cannabis_loc_scaffold",[[1,21642,22444,1,"100.0","tig00006085.g28.t1.mrna1","100.0","0","417","0","tig00006085.g28.t1","tig00006085_overlapping_hits_sub_region","cannabis_loc_scaffold",[[2,21642,21658,1,"tig00006085.g28.t1.mrna1.exon1","tig00006085.g28.t1",100,"tig00006085_overlapping_hits_sub_region","cannabis_loc_scaffold","tig00006085.g28.t1 1 16 +","exon"],[2,22043,22444,1,"tig00006085.g28.t1.mrna1.exon2","tig00006085.g28.t1",100,"tig00006085_overlapping_hits_sub_region","cannabis_loc_scaffold","tig00006085.g28.t1 17 417 +","exon"],[3,21642,21658,1,"tig00006085.g28.t1.mrna1.cds1","tig00006085.g28.t1",0,100,"tig00006085_overlapping_hits_sub_region","cannabis_loc_scaffold","tig00006085.g28.t1 1 16 +","CDS"],[3,22043,22444,1,"tig00006085.g28.t1.mrna1.cds2","tig00006085.g28.t1",1,100,"tig00006085_overlapping_hits_sub_region","cannabis_loc_scaffold","tig00006085.g28.t1 17 417 +","CDS"]],"mRNA","0"]],"gene"],[0,26588,31001,-1,"tig00006085.g29.t1.path1","tig00006085.g29.t1","tig00006085_overlapping_hits_sub_region","cannabis_loc_scaffold",[[1,26588,31001,-1,"100.0","tig00006085.g29.t1.mrna1","100.0","0","3291","0","tig00006085.g29.t1","tig00006085_overlapping_hits_sub_region","cannabis_loc_scaffold",[[2,30497,31001,-1,"tig00006085.g29.t1.mrna1.exon1","tig00006085.g29.t1",100,"tig00006085_overlapping_hits_sub_region","cannabis_loc_scaffold","tig00006085.g29.t1 1 504 +","exon"],[2,30066,30409,-1,"tig00006085.g29.t1.mrna1.exon2","tig00006085.g29.t1",100,"tig00006085_overlapping_hits_sub_region","cannabis_loc_scaffold","tig00006085.g29.t1 505 847 +","exon"],[2,29734,29976,-1,"tig00006085.g29.t1.mrna1.exon3","tig00006085.g29.t1",100,"tig00006085_overlapping_hits_sub_region","cannabis_loc_scaffold","tig00006085.g29.t1 848 1089 +","exon"],[2,29503,29645,-1,"tig00006085.g29.t1.mrna1.exon4","tig00006085.g29.t1",100,"tig00006085_overlapping_hits_sub_region","cannabis_loc_scaffold","tig00006085.g29.t1 1090 1231 +","exon"],[2,29067,29333,-1,"tig00006085.g29.t1.mrna1.exon5","tig00006085.g29.t1",100,"tig00006085_overlapping_hits_sub_region","cannabis_loc_scaffold","tig00006085.g29.t1 1232 1497 +","exon"],[2,28664,28936,-1,"tig00006085.g29.t1.mrna1.exon6","tig00006085.g29.t1",100,"tig00006085_overlapping_hits_sub_region","cannabis_loc_scaffold","tig00006085.g29.t1 1498 1769 +","exon"],[2,27893,28586,-1,"tig00006085.g29.t1.mrna1.exon7","tig00006085.g29.t1",100,"tig00006085_overlapping_hits_sub_region","cannabis_loc_scaffold","tig00006085.g29.t1 1770 2462 +","exon"],[2,27590,27702,-1,"tig00006085.g29.t1.mrna1.exon8","tig00006085.g29.t1",100,"tig00006085_overlapping_hits_sub_region","cannabis_loc_scaffold","tig00006085.g29.t1 2463 2574 +","exon"],[2,27062,27475,-1,"tig00006085.g29.t1.mrna1.exon9","tig00006085.g29.t1",100,"tig00006085_overlapping_hits_sub_region","cannabis_loc_scaffold","tig00006085.g29.t1 2575 2987 +","exon"],[2,26905,26971,-1,"tig00006085.g29.t1.mrna1.exon10","tig00006085.g29.t1",100,"tig00006085_overlapping_hits_sub_region","cannabis_loc_scaffold","tig00006085.g29.t1 2988 3053 +","exon"],[2,26588,26826,-1,"tig00006085.g29.t1.mrna1.exon11","tig00006085.g29.t1",100,"tig00006085_overlapping_hits_sub_region","cannabis_loc_scaffold","tig00006085.g29.t1 3054 3291 +","exon"],[3,30497,31001,-1,"tig00006085.g29.t1.mrna1.cds1","tig00006085.g29.t1",0,100,"tig00006085_overlapping_hits_sub_region","cannabis_loc_scaffold","tig00006085.g29.t1 1 504 +","CDS"],[3,30066,30409,-1,"tig00006085.g29.t1.mrna1.cds2","tig00006085.g29.t1",0,100,"tig00006085_overlapping_hits_sub_region","cannabis_loc_scaffold","tig00006085.g29.t1 505 847 +","CDS"],[3,29734,29976,-1,"tig00006085.g29.t1.mrna1.cds3","tig00006085.g29.t1",1,100,"tig00006085_overlapping_hits_sub_region","cannabis_loc_scaffold","tig00006085.g29.t1 848 1089 +","CDS"],[3,29503,29645,-1,"tig00006085.g29.t1.mrna1.cds4","tig00006085.g29.t1",0,100,"tig00006085_overlapping_hits_sub_region","cannabis_loc_scaffold","tig00006085.g29.t1 1090 1231 +","CDS"],[3,29067,29333,-1,"tig00006085.g29.t1.mrna1.cds5","tig00006085.g29.t1",1,100,"tig00006085_overlapping_hits_sub_region","cannabis_loc_scaffold","tig00006085.g29.t1 1232 1497 +","CDS"],[3,28664,28936,-1,"tig00006085.g29.t1.mrna1.cds6","tig00006085.g29.t1",0,100,"tig00006085_overlapping_hits_sub_region","cannabis_loc_scaffold","tig00006085.g29.t1 1498 1769 +","CDS"],[3,27893,28586,-1,"tig00006085.g29.t1.mrna1.cds7","tig00006085.g29.t1",2,100,"tig00006085_overlapping_hits_sub_region","cannabis_loc_scaffold","tig00006085.g29.t1 1770 2462 +","CDS"],[3,27590,27702,-1,"tig00006085.g29.t1.mrna1.cds8","tig00006085.g29.t1",2,100,"tig00006085_overlapping_hits_sub_region","cannabis_loc_scaffold","tig00006085.g29.t1 2463 2574 +","CDS"],[3,27062,27475,-1,"tig00006085.g29.t1.mrna1.cds9","tig00006085.g29.t1",0,100,"tig00006085_overlapping_hits_sub_region","cannabis_loc_scaffold","tig00006085.g29.t1 2575 2987 +","CDS"],[3,26905,26971,-1,"tig00006085.g29.t1.mrna1.cds10","tig00006085.g29.t1",2,100,"tig00006085_overlapping_hits_sub_region","cannabis_loc_scaffold","tig00006085.g29.t1 2988 3053 +","CDS"],[3,26588,26826,-1,"tig00006085.g29.t1.mrna1.cds11","tig00006085.g29.t1",2,100,"tig00006085_overlapping_hits_sub_region","cannabis_loc_scaffold","tig00006085.g29.t1 3054 3291 +","CDS"]],"mRNA","0"]],"gene"],[0,36558,38871,1,"tig00006085.g31.t1.path1","tig00006085.g31.t1","tig00006085_overlapping_hits_sub_region","cannabis_loc_scaffold",[[1,36558,38871,1,"100.0","tig00006085.g31.t1.mrna1","100.0","0","1035","0","tig00006085.g31.t1","tig00006085_overlapping_hits_sub_region","cannabis_loc_scaffold",[[2,36558,36687,1,"tig00006085.g31.t1.mrna1.exon1","tig00006085.g31.t1",100,"tig00006085_overlapping_hits_sub_region","cannabis_loc_scaffold","tig00006085.g31.t1 1 129 +","exon"],[2,36882,36913,1,"tig00006085.g31.t1.mrna1.exon2","tig00006085.g31.t1",100,"tig00006085_overlapping_hits_sub_region","cannabis_loc_scaffold","tig00006085.g31.t1 130 160 +","exon"],[2,37296,37487,1,"tig00006085.g31.t1.mrna1.exon3","tig00006085.g31.t1",100,"tig00006085_overlapping_hits_sub_region","cannabis_loc_scaffold","tig00006085.g31.t1 161 351 +","exon"],[2,37672,37789,1,"tig00006085.g31.t1.mrna1.exon4","tig00006085.g31.t1",100,"tig00006085_overlapping_hits_sub_region","cannabis_loc_scaffold","tig00006085.g31.t1 352 468 +","exon"],[2,37877,38003,1,"tig00006085.g31.t1.mrna1.exon5","tig00006085.g31.t1",100,"tig00006085_overlapping_hits_sub_region","cannabis_loc_scaffold","tig00006085.g31.t1 469 594 +","exon"],[2,38206,38362,1,"tig00006085.g31.t1.mrna1.exon6","tig00006085.g31.t1",100,"tig00006085_overlapping_hits_sub_region","cannabis_loc_scaffold","tig00006085.g31.t1 595 750 +","exon"],[2,38586,38871,1,"tig00006085.g31.t1.mrna1.exon7","tig00006085.g31.t1",100,"tig00006085_overlapping_hits_sub_region","cannabis_loc_scaffold","tig00006085.g31.t1 751 1035 +","exon"],[3,36558,36687,1,"tig00006085.g31.t1.mrna1.cds1","tig00006085.g31.t1",0,100,"tig00006085_overlapping_hits_sub_region","cannabis_loc_scaffold","tig00006085.g31.t1 1 129 +","CDS"],[3,36882,36913,1,"tig00006085.g31.t1.mrna1.cds2","tig00006085.g31.t1",0,100,"tig00006085_overlapping_hits_sub_region","cannabis_loc_scaffold","tig00006085.g31.t1 130 160 +","CDS"],[3,37296,37487,1,"tig00006085.g31.t1.mrna1.cds3","tig00006085.g31.t1",1,100,"tig00006085_overlapping_hits_sub_region","cannabis_loc_scaffold","tig00006085.g31.t1 161 351 +","CDS"],[3,37672,37789,1,"tig00006085.g31.t1.mrna1.cds4","tig00006085.g31.t1",0,100,"tig00006085_overlapping_hits_sub_region","cannabis_loc_scaffold","tig00006085.g31.t1 352 468 +","CDS"],[3,37877,38003,1,"tig00006085.g31.t1.mrna1.cds5","tig00006085.g31.t1",0,100,"tig00006085_overlapping_hits_sub_region","cannabis_loc_scaffold","tig00006085.g31.t1 469 594 +","CDS"],[3,38206,38362,1,"tig00006085.g31.t1.mrna1.cds6","tig00006085.g31.t1",0,100,"tig00006085_overlapping_hits_sub_region","cannabis_loc_scaffold","tig00006085.g31.t1 595 750 +","CDS"],[3,38586,38871,1,"tig00006085.g31.t1.mrna1.cds7","tig00006085.g31.t1",0,100,"tig00006085_overlapping_hits_sub_region","cannabis_loc_scaffold","tig00006085.g31.t1 751 1035 +","CDS"]],"mRNA","0"]],"gene"]],"urlTemplate":"lf-{Chunk}.json"}}