{"featureCount":1,"formatVersion":1,"histograms":{"meta":[{"arrayParams":{"chunkSize":10000,"length":1,"urlTemplate":"hist-50000-{Chunk}.json"},"basesPerBin":"50000"}],"stats":[{"basesPerBin":"50000","max":1,"mean":1}]},"intervals":{"classes":[{"attributes":["Start","End","Strand","Id","Name","Seq_id","Source","Subfeatures","Type"],"isArrayAttr":{"Subfeatures":1}},{"attributes":["Start","End","Strand","Coverage","Id","Identity","Indels","Matches","Mismatches","Name","Seq_id","Source","Subfeatures","Type","Unknowns"],"isArrayAttr":{"Subfeatures":1}},{"attributes":["Start","End","Strand","Id","Name","Score","Seq_id","Source","Target","Type"],"isArrayAttr":{}},{"attributes":["Start","End","Strand","Id","Name","Phase","Score","Seq_id","Source","Target","Type"],"isArrayAttr":{}},{"attributes":["Start","End","Chunk"],"isArrayAttr":{"Sublist":1}}],"count":1,"lazyClass":4,"maxEnd":13787,"minStart":9171,"nclist":[[0,9171,13787,1,"tig00001940.g59.t1.path1","tig00001940.g59.t1","tig00001940_overlapping_hits_sub_region","cannabis_loc_scaffold",[[1,9171,13787,1,"100.0","tig00001940.g59.t1.mrna1","100.0","0","3084","0","tig00001940.g59.t1","tig00001940_overlapping_hits_sub_region","cannabis_loc_scaffold",[[2,9171,9267,1,"tig00001940.g59.t1.mrna1.exon1","tig00001940.g59.t1",100,"tig00001940_overlapping_hits_sub_region","cannabis_loc_scaffold","tig00001940.g59.t1 1 96 +","exon"],[2,9382,9451,1,"tig00001940.g59.t1.mrna1.exon2","tig00001940.g59.t1",100,"tig00001940_overlapping_hits_sub_region","cannabis_loc_scaffold","tig00001940.g59.t1 97 165 +","exon"],[2,9540,9599,1,"tig00001940.g59.t1.mrna1.exon3","tig00001940.g59.t1",100,"tig00001940_overlapping_hits_sub_region","cannabis_loc_scaffold","tig00001940.g59.t1 166 224 +","exon"],[2,9673,9848,1,"tig00001940.g59.t1.mrna1.exon4","tig00001940.g59.t1",100,"tig00001940_overlapping_hits_sub_region","cannabis_loc_scaffold","tig00001940.g59.t1 225 399 +","exon"],[2,9921,10031,1,"tig00001940.g59.t1.mrna1.exon5","tig00001940.g59.t1",100,"tig00001940_overlapping_hits_sub_region","cannabis_loc_scaffold","tig00001940.g59.t1 400 509 +","exon"],[2,10272,10347,1,"tig00001940.g59.t1.mrna1.exon6","tig00001940.g59.t1",100,"tig00001940_overlapping_hits_sub_region","cannabis_loc_scaffold","tig00001940.g59.t1 510 584 +","exon"],[2,10552,10667,1,"tig00001940.g59.t1.mrna1.exon7","tig00001940.g59.t1",100,"tig00001940_overlapping_hits_sub_region","cannabis_loc_scaffold","tig00001940.g59.t1 585 699 +","exon"],[2,10758,11157,1,"tig00001940.g59.t1.mrna1.exon8","tig00001940.g59.t1",100,"tig00001940_overlapping_hits_sub_region","cannabis_loc_scaffold","tig00001940.g59.t1 700 1098 +","exon"],[2,11234,11821,1,"tig00001940.g59.t1.mrna1.exon9","tig00001940.g59.t1",100,"tig00001940_overlapping_hits_sub_region","cannabis_loc_scaffold","tig00001940.g59.t1 1099 1685 +","exon"],[2,11925,12113,1,"tig00001940.g59.t1.mrna1.exon10","tig00001940.g59.t1",100,"tig00001940_overlapping_hits_sub_region","cannabis_loc_scaffold","tig00001940.g59.t1 1686 1873 +","exon"],[2,12185,12314,1,"tig00001940.g59.t1.mrna1.exon11","tig00001940.g59.t1",100,"tig00001940_overlapping_hits_sub_region","cannabis_loc_scaffold","tig00001940.g59.t1 1874 2002 +","exon"],[2,12399,12748,1,"tig00001940.g59.t1.mrna1.exon12","tig00001940.g59.t1",100,"tig00001940_overlapping_hits_sub_region","cannabis_loc_scaffold","tig00001940.g59.t1 2003 2351 +","exon"],[2,12827,12924,1,"tig00001940.g59.t1.mrna1.exon13","tig00001940.g59.t1",100,"tig00001940_overlapping_hits_sub_region","cannabis_loc_scaffold","tig00001940.g59.t1 2352 2448 +","exon"],[2,12992,13203,1,"tig00001940.g59.t1.mrna1.exon14","tig00001940.g59.t1",100,"tig00001940_overlapping_hits_sub_region","cannabis_loc_scaffold","tig00001940.g59.t1 2449 2659 +","exon"],[2,13267,13475,1,"tig00001940.g59.t1.mrna1.exon15","tig00001940.g59.t1",100,"tig00001940_overlapping_hits_sub_region","cannabis_loc_scaffold","tig00001940.g59.t1 2660 2867 +","exon"],[2,13570,13787,1,"tig00001940.g59.t1.mrna1.exon16","tig00001940.g59.t1",100,"tig00001940_overlapping_hits_sub_region","cannabis_loc_scaffold","tig00001940.g59.t1 2868 3084 +","exon"],[3,9171,9267,1,"tig00001940.g59.t1.mrna1.cds1","tig00001940.g59.t1",0,100,"tig00001940_overlapping_hits_sub_region","cannabis_loc_scaffold","tig00001940.g59.t1 1 96 +","CDS"],[3,9382,9451,1,"tig00001940.g59.t1.mrna1.cds2","tig00001940.g59.t1",0,100,"tig00001940_overlapping_hits_sub_region","cannabis_loc_scaffold","tig00001940.g59.t1 97 165 +","CDS"],[3,9540,9599,1,"tig00001940.g59.t1.mrna1.cds3","tig00001940.g59.t1",0,100,"tig00001940_overlapping_hits_sub_region","cannabis_loc_scaffold","tig00001940.g59.t1 166 224 +","CDS"],[3,9673,9848,1,"tig00001940.g59.t1.mrna1.cds4","tig00001940.g59.t1",2,100,"tig00001940_overlapping_hits_sub_region","cannabis_loc_scaffold","tig00001940.g59.t1 225 399 +","CDS"],[3,9921,10031,1,"tig00001940.g59.t1.mrna1.cds5","tig00001940.g59.t1",0,100,"tig00001940_overlapping_hits_sub_region","cannabis_loc_scaffold","tig00001940.g59.t1 400 509 +","CDS"],[3,10272,10347,1,"tig00001940.g59.t1.mrna1.cds6","tig00001940.g59.t1",2,100,"tig00001940_overlapping_hits_sub_region","cannabis_loc_scaffold","tig00001940.g59.t1 510 584 +","CDS"],[3,10552,10667,1,"tig00001940.g59.t1.mrna1.cds7","tig00001940.g59.t1",2,100,"tig00001940_overlapping_hits_sub_region","cannabis_loc_scaffold","tig00001940.g59.t1 585 699 +","CDS"],[3,10758,11157,1,"tig00001940.g59.t1.mrna1.cds8","tig00001940.g59.t1",0,100,"tig00001940_overlapping_hits_sub_region","cannabis_loc_scaffold","tig00001940.g59.t1 700 1098 +","CDS"],[3,11234,11821,1,"tig00001940.g59.t1.mrna1.cds9","tig00001940.g59.t1",0,100,"tig00001940_overlapping_hits_sub_region","cannabis_loc_scaffold","tig00001940.g59.t1 1099 1685 +","CDS"],[3,11925,12113,1,"tig00001940.g59.t1.mrna1.cds10","tig00001940.g59.t1",2,100,"tig00001940_overlapping_hits_sub_region","cannabis_loc_scaffold","tig00001940.g59.t1 1686 1873 +","CDS"],[3,12185,12314,1,"tig00001940.g59.t1.mrna1.cds11","tig00001940.g59.t1",1,100,"tig00001940_overlapping_hits_sub_region","cannabis_loc_scaffold","tig00001940.g59.t1 1874 2002 +","CDS"],[3,12399,12748,1,"tig00001940.g59.t1.mrna1.cds12","tig00001940.g59.t1",1,100,"tig00001940_overlapping_hits_sub_region","cannabis_loc_scaffold","tig00001940.g59.t1 2003 2351 +","CDS"],[3,12827,12924,1,"tig00001940.g59.t1.mrna1.cds13","tig00001940.g59.t1",2,100,"tig00001940_overlapping_hits_sub_region","cannabis_loc_scaffold","tig00001940.g59.t1 2352 2448 +","CDS"],[3,12992,13203,1,"tig00001940.g59.t1.mrna1.cds14","tig00001940.g59.t1",0,100,"tig00001940_overlapping_hits_sub_region","cannabis_loc_scaffold","tig00001940.g59.t1 2449 2659 +","CDS"],[3,13267,13475,1,"tig00001940.g59.t1.mrna1.cds15","tig00001940.g59.t1",1,100,"tig00001940_overlapping_hits_sub_region","cannabis_loc_scaffold","tig00001940.g59.t1 2660 2867 +","CDS"],[3,13570,13787,1,"tig00001940.g59.t1.mrna1.cds16","tig00001940.g59.t1",2,100,"tig00001940_overlapping_hits_sub_region","cannabis_loc_scaffold","tig00001940.g59.t1 2868 3084 +","CDS"]],"mRNA","0"]],"gene"]],"urlTemplate":"lf-{Chunk}.json"}}